Workbook

Sheet Executive Summary
A1: TRADE FINANCE PORTFOLIO QUALITY REPORT — EXECUTIVE SUMMARY
A2: Group HQ: Abu Dhabi, UAE | Entities: Samman Capital, FWBL, Beltone, Mirabank, Lulo Bank | Report Date: Feb 2025 | Currency: USD (mm)
A4: 1. GROUP PORTFOLIO KPIs
A5: Metric | B5: Current Month | C5: Prev Month | D5: MoM Change | E5: MoM % | H5: Risk Metric | I5: Value | J5: Threshold | K5: RAG
A6: Total Facilities | B6: =COUNTA('Raw Data'!A2:A81) -> 80 | C6: 78 | D6: =B6-C6 -> 2 | E6: =IF(C6=0,"-",D6/C6) -> 0.025641026 | H6: NPL Ratio (Stage 3/Total) | I6: =SUMIFS('Raw Data'!K2:K81,'Raw Data'!S2:S81,"Stage 3")/SUM('Raw Data'!K2:K81) -> 0.002306768 | J6: 0.03 | K6: =IF(I6<=J6,"🟢 Green",IF(I6<=J6*1.5,"🟡 Amber","🔴 Red")) -> 🟢 Green
A7: Total Outstanding (USD mm) | B7: =SUM('Raw Data'!K2:K81) -> 1556.29 | C7: =SUM('Raw Data'!L2:L81) -> 1588.69 | D7: =B7-C7 -> -32.4 | E7: =IF(C7=0,"-",D7/C7) -> -0.020394161 | H7: Stage 2 Ratio | I7: =SUMIFS('Raw Data'!K2:K81,'Raw Data'!S2:S81,"Stage 2")/SUM('Raw Data'!K2:K81) -> 0.1141304 | J7: 0.08 | K7: =IF(I7<=J7,"🟢 Green",IF(I7<=J7*1.5,"🟡 Amber","🔴 Red")) -> 🟡 Amber
A8: Total Provisions (USD mm) | B8: =SUM('Raw Data'!U2:U81) -> 34.86 | C8: =B8*0.92 -> 32.0712 | D8: =B8-C8 -> 2.7888 | E8: =IF(C8=0,"-",D8/C8) -> 0.086956522 | H8: Watchlist Accounts | I8: =COUNTIFS('Raw Data'!Z2:Z81,"Yes") -> 9 | J8: 8 | K8: =IF(I8<=J8,"🟢 Green",IF(I8<=J8*1.25,"🟡 Amber","🔴 Red")) -> 🟡 Amber
A9: Wtd Avg Rating (1=best, 10=worst) | B9: {=SUMPRODUCT('Raw Data'!P2:P81*1,'Raw Data'!K2:K81)/SUM('Raw Data'!K2:K81)} -> 4.8438723 | C9: 4.8 | D9: =B9-C9 -> 0.043872286 | E9: =IF(C9=0,"-",D9/C9) -> 0.0091400596 | H9: Watchlist Exposure (USD mm) | I9: =SUMIFS('Raw Data'!K2:K81,'Raw Data'!Z2:Z81,"Yes") -> 181.21 | J9: 100 | K9: =IF(I9<=J9,"🟢 Green",IF(I9<=J9*1.25,"🟡 Amber","🔴 Red")) -> 🔴 Red
A10: Avg Utilization Rate | B10: =SUM('Raw Data'!K2:K81)/SUM('Raw Data'!J2:J81) -> 0.81917761 | C10: 0.78 | D10: =B10-C10 -> 0.039177606 | E10: =IF(C10=0,"-",D10/C10) -> 0.0502277 | H10: Avg Collateral Coverage | I10: =AVERAGE('Raw Data'!W2:W81) -> 0.842625 | J10: 0.8 | K10: =IF(I10>=J10,"🟢 Green",IF(I10>=J10*0.9,"🟡 Amber","🔴 Red")) -> 🟢 Green
A11: Avg Tenor (Days) | B11: =AVERAGE('Raw Data'!M2:M81) -> 125.125 | C11: 125 | D11: =B11-C11 -> 0.125 | E11: =IF(C11=0,"-",D11/C11) -> 0.001 | H11: Wtd Avg Risk Weight | I11: =SUMPRODUCT('Raw Data'!X2:X81,'Raw Data'!K2:K81)/SUM('Raw Data'!K2:K81) -> 0.53278534 | J11: 0.55 | K11: =IF(I11<=J11,"🟢 Green",IF(I11<=J11*1.1,"🟡 Amber","🔴 Red")) -> 🟢 Green
A13: 2. ENTITY-LEVEL SCORECARD (Subsidiary Performance)
A14: Entity | B14: Geography | C14: # Facilities | D14: Outstanding (USD mm) | E14: % of Group | F14: MoM Chg % | G14: Stage 2+3 % | H14: Wtd Avg Rating | I14: Avg Collateral Cov. | J14: Watchlist # | K14: Provisions (USD mm) | L14: Entity RAG
A15: Samman Capital | B15: India / Cross-border | C15: =COUNTIFS('Raw Data'!B$2:B$81,$A15) -> 29 | D15: =SUMIFS('Raw Data'!K$2:K$81,'Raw Data'!B$2:B$81,$A15) -> 558.09 | E15: =D15/$B$7 -> 0.35860283 | F15: =IF(SUMIFS('Raw Data'!L$2:L$81,'Raw Data'!B$2:B$81,$A15)=0,"-",(D15-SUMIFS('Raw Data'!L$2:L$81,'Raw Data'!B$2:B$81,$A15))/SUMIFS('Raw Data'!L$2:L$81,'Raw Data'!B$2:B$81,$A15)) -> -0.033359314 | G15: =IF(D15=0,"-",(SUMIFS('Raw Data'!K$2:K$81,'Raw Data'!B$2:B$81,$A15,'Raw Data'!S$2:S$81,"Stage 2")+SUMIFS('Raw Data'!K$2:K$81,'Raw Data'!B$2:B$81,$A15,'Raw Data'!S$2:S$81,"Stage 3"))/D15) -> 0.0037090792 | H15: {=IF(C15=0,"-",SUMPRODUCT(('Raw Data'!B$2:B$81=$A15)*('Raw Data'!P$2:P$81*1)*('Raw Data'!K$2:K$81))/D15)} -> 4.5330323 | I15: =IF(C15=0,"-",AVERAGEIFS('Raw Data'!W$2:W$81,'Raw Data'!B$2:B$81,$A15)) -> 0.83862069 | J15: =COUNTIFS('Raw Data'!B$2:B$81,$A15,'Raw Data'!Z$2:Z$81,"Yes") -> 1 | K15: =SUMIFS('Raw Data'!U$2:U$81,'Raw Data'!B$2:B$81,$A15) -> 7.57 | L15: =IF(G15>0.15,"🔴 Red",IF(G15>0.08,"🟡 Amber","🟢 Green")) -> 🟢 Green
A16: First Women Bank Ltd (FWBL) | B16: Pakistan / Cross-border | C16: =COUNTIFS('Raw Data'!B$2:B$81,$A16) -> 12 | D16: =SUMIFS('Raw Data'!K$2:K$81,'Raw Data'!B$2:B$81,$A16) -> 198.29 | E16: =D16/$B$7 -> 0.12741199 | F16: =IF(SUMIFS('Raw Data'!L$2:L$81,'Raw Data'!B$2:B$81,$A16)=0,"-",(D16-SUMIFS('Raw Data'!L$2:L$81,'Raw Data'!B$2:B$81,$A16))/SUMIFS('Raw Data'!L$2:L$81,'Raw Data'!B$2:B$81,$A16)) -> -0.060682141 | G16: =IF(D16=0,"-",(SUMIFS('Raw Data'!K$2:K$81,'Raw Data'!B$2:B$81,$A16,'Raw Data'!S$2:S$81,"Stage 2")+SUMIFS('Raw Data'!K$2:K$81,'Raw Data'!B$2:B$81,$A16,'Raw Data'!S$2:S$81,"Stage 3"))/D16) -> 0.050935499 | H16: {=IF(C16=0,"-",SUMPRODUCT(('Raw Data'!B$2:B$81=$A16)*('Raw Data'!P$2:P$81*1)*('Raw Data'!K$2:K$81))/D16)} -> 5.3078824 | I16: =IF(C16=0,"-",AVERAGEIFS('Raw Data'!W$2:W$81,'Raw Data'!B$2:B$81,$A16)) -> 0.85916667 | J16: =COUNTIFS('Raw Data'!B$2:B$81,$A16,'Raw Data'!Z$2:Z$81,"Yes") -> 2 | K16: =SUMIFS('Raw Data'!U$2:U$81,'Raw Data'!B$2:B$81,$A16) -> 4.71 | L16: =IF(G16>0.15,"🔴 Red",IF(G16>0.08,"🟡 Amber","🟢 Green")) -> 🟢 Green
A17: Beltone | B17: Egypt / Africa | C17: =COUNTIFS('Raw Data'!B$2:B$81,$A17) -> 19 | D17: =SUMIFS('Raw Data'!K$2:K$81,'Raw Data'!B$2:B$81,$A17) -> 433.57 | E17: =D17/$B$7 -> 0.27859204 | F17: =IF(SUMIFS('Raw Data'!L$2:L$81,'Raw Data'!B$2:B$81,$A17)=0,"-",(D17-SUMIFS('Raw Data'!L$2:L$81,'Raw Data'!B$2:B$81,$A17))/SUMIFS('Raw Data'!L$2:L$81,'Raw Data'!B$2:B$81,$A17)) -> 0.0035877969 | G17: =IF(D17=0,"-",(SUMIFS('Raw Data'!K$2:K$81,'Raw Data'!B$2:B$81,$A17,'Raw Data'!S$2:S$81,"Stage 2")+SUMIFS('Raw Data'!K$2:K$81,'Raw Data'!B$2:B$81,$A17,'Raw Data'!S$2:S$81,"Stage 3"))/D17) -> 0.33475563 | H17: {=IF(C17=0,"-",SUMPRODUCT(('Raw Data'!B$2:B$81=$A17)*('Raw Data'!P$2:P$81*1)*('Raw Data'!K$2:K$81))/D17)} -> 5.8177226 | I17: =IF(C17=0,"-",AVERAGEIFS('Raw Data'!W$2:W$81,'Raw Data'!B$2:B$81,$A17)) -> 0.79578947 | J17: =COUNTIFS('Raw Data'!B$2:B$81,$A17,'Raw Data'!Z$2:Z$81,"Yes") -> 5 | K17: =SUMIFS('Raw Data'!U$2:U$81,'Raw Data'!B$2:B$81,$A17) -> 15.98 | L17: =IF(G17>0.15,"🔴 Red",IF(G17>0.08,"🟡 Amber","🟢 Green")) -> 🔴 Red
A18: Mirabank | B18: Serbia / Baltics / Europe | C18: =COUNTIFS('Raw Data'!B$2:B$81,$A18) -> 18 | D18: =SUMIFS('Raw Data'!K$2:K$81,'Raw Data'!B$2:B$81,$A18) -> 333.65 | E18: =D18/$B$7 -> 0.21438806 | F18: =IF(SUMIFS('Raw Data'!L$2:L$81,'Raw Data'!B$2:B$81,$A18)=0,"-",(D18-SUMIFS('Raw Data'!L$2:L$81,'Raw Data'!B$2:B$81,$A18))/SUMIFS('Raw Data'!L$2:L$81,'Raw Data'!B$2:B$81,$A18)) -> -0.0095291813 | G18: =IF(D18=0,"-",(SUMIFS('Raw Data'!K$2:K$81,'Raw Data'!B$2:B$81,$A18,'Raw Data'!S$2:S$81,"Stage 2")+SUMIFS('Raw Data'!K$2:K$81,'Raw Data'!B$2:B$81,$A18,'Raw Data'!S$2:S$81,"Stage 3"))/D18) -> 0.07163195 | H18: {=IF(C18=0,"-",SUMPRODUCT(('Raw Data'!B$2:B$81=$A18)*('Raw Data'!P$2:P$81*1)*('Raw Data'!K$2:K$81))/D18)} -> 3.9808482 | I18: =IF(C18=0,"-",AVERAGEIFS('Raw Data'!W$2:W$81,'Raw Data'!B$2:B$81,$A18)) -> 0.87555556 | J18: =COUNTIFS('Raw Data'!B$2:B$81,$A18,'Raw Data'!Z$2:Z$81,"Yes") -> 1 | K18: =SUMIFS('Raw Data'!U$2:U$81,'Raw Data'!B$2:B$81,$A18) -> 6.38 | L18: =IF(G18>0.15,"🔴 Red",IF(G18>0.08,"🟡 Amber","🟢 Green")) -> 🟢 Green
A19: Lulo Bank | B19: Colombia (minimal TF) | C19: =COUNTIFS('Raw Data'!B$2:B$81,$A19) -> 2 | D19: =SUMIFS('Raw Data'!K$2:K$81,'Raw Data'!B$2:B$81,$A19) -> 32.69 | E19: =D19/$B$7 -> 0.021005083 | F19: =IF(SUMIFS('Raw Data'!L$2:L$81,'Raw Data'!B$2:B$81,$A19)=0,"-",(D19-SUMIFS('Raw Data'!L$2:L$81,'Raw Data'!B$2:B$81,$A19))/SUMIFS('Raw Data'!L$2:L$81,'Raw Data'!B$2:B$81,$A19)) -> 0.042410714 | G19: =IF(D19=0,"-",(SUMIFS('Raw Data'!K$2:K$81,'Raw Data'!B$2:B$81,$A19,'Raw Data'!S$2:S$81,"Stage 2")+SUMIFS('Raw Data'!K$2:K$81,'Raw Data'!B$2:B$81,$A19,'Raw Data'!S$2:S$81,"Stage 3"))/D19) -> 0 | H19: {=IF(C19=0,"-",SUMPRODUCT(('Raw Data'!B$2:B$81=$A19)*('Raw Data'!P$2:P$81*1)*('Raw Data'!K$2:K$81))/D19)} -> 3.2282043 | I19: =IF(C19=0,"-",AVERAGEIFS('Raw Data'!W$2:W$81,'Raw Data'!B$2:B$81,$A19)) -> 0.95 | J19: =COUNTIFS('Raw Data'!B$2:B$81,$A19,'Raw Data'!Z$2:Z$81,"Yes") -> 0 | K19: =SUMIFS('Raw Data'!U$2:U$81,'Raw Data'!B$2:B$81,$A19) -> 0.22 | L19: =IF(G19>0.15,"🔴 Red",IF(G19>0.08,"🟡 Amber","🟢 Green")) -> 🟢 Green
A20: GROUP TOTAL | C20: =SUM(C15:C19) -> 80 | D20: =SUM(D15:D19) -> 1556.29 | E20: =SUM(E15:E19) -> 1 | F20: =IF($C$7=0,"-",(D20-$C$7)/$C$7) -> -0.020394161 | G20: =IF(D20=0,"-",(SUMIFS('Raw Data'!K$2:K$81,'Raw Data'!S$2:S$81,"Stage 2")+SUMIFS('Raw Data'!K$2:K$81,'Raw Data'!S$2:S$81,"Stage 3"))/D20) -> 0.11643717 | H20: =$B$9 -> 4.8438723 | I20: =$I$10 -> 0.842625 | J20: =SUM(J15:J19) -> 9 | K20: =SUM(K15:K19) -> 34.86

Sheet Entity Performance
A1: ENTITY PERFORMANCE — SUBSIDIARY DEEP DIVE
A2: Entity-level portfolio breakdown with product mix, staging, and limits per subsidiary
A4: 1. ENTITY LIMIT UTILIZATION & ALLOCATION
A5: Entity | B5: Geography | C5: Group Approved Limit (USD mm) | D5: Outstanding (USD mm) | E5: Headroom (USD mm) | F5: Utilization % | G5: Stage 1 (USD mm) | H5: Stage 2 (USD mm) | I5: Stage 3 (USD mm) | J5: Provisions (USD mm) | K5: Prov. Coverage | L5: RAG Status
A6: Samman Capital | B6: India / Cross-border | C6: 700 | D6: =SUMIFS('Raw Data'!K$2:K$81,'Raw Data'!B$2:B$81,$A6) -> 558.09 | E6: =C6-D6 -> 141.91 | F6: =D6/C6 -> 0.79727143 | G6: =SUMIFS('Raw Data'!K$2:K$81,'Raw Data'!B$2:B$81,$A6,'Raw Data'!S$2:S$81,"Stage 1") -> 556.02 | H6: =SUMIFS('Raw Data'!K$2:K$81,'Raw Data'!B$2:B$81,$A6,'Raw Data'!S$2:S$81,"Stage 2") -> 2.07 | I6: =SUMIFS('Raw Data'!K$2:K$81,'Raw Data'!B$2:B$81,$A6,'Raw Data'!S$2:S$81,"Stage 3") -> 0 | J6: =SUMIFS('Raw Data'!U$2:U$81,'Raw Data'!B$2:B$81,$A6) -> 7.57 | K6: =IF(D6=0,"-",J6/D6) -> 0.01356412 | L6: =IF(F6>=0.85,"🔴 CRITICAL",IF(F6>=0.7,"🟡 WARNING","🟢 NORMAL")) -> 🟡 WARNING
A7: First Women Bank Ltd (FWBL) | B7: Pakistan / Cross-border | C7: 300 | D7: =SUMIFS('Raw Data'!K$2:K$81,'Raw Data'!B$2:B$81,$A7) -> 198.29 | E7: =C7-D7 -> 101.71 | F7: =D7/C7 -> 0.66096667 | G7: =SUMIFS('Raw Data'!K$2:K$81,'Raw Data'!B$2:B$81,$A7,'Raw Data'!S$2:S$81,"Stage 1") -> 188.19 | H7: =SUMIFS('Raw Data'!K$2:K$81,'Raw Data'!B$2:B$81,$A7,'Raw Data'!S$2:S$81,"Stage 2") -> 6.51 | I7: =SUMIFS('Raw Data'!K$2:K$81,'Raw Data'!B$2:B$81,$A7,'Raw Data'!S$2:S$81,"Stage 3") -> 3.59 | J7: =SUMIFS('Raw Data'!U$2:U$81,'Raw Data'!B$2:B$81,$A7) -> 4.71 | K7: =IF(D7=0,"-",J7/D7) -> 0.023753089 | L7: =IF(F7>=0.85,"🔴 CRITICAL",IF(F7>=0.7,"🟡 WARNING","🟢 NORMAL")) -> 🟢 NORMAL
A8: Beltone | B8: Egypt / Africa | C8: 500 | D8: =SUMIFS('Raw Data'!K$2:K$81,'Raw Data'!B$2:B$81,$A8) -> 433.57 | E8: =C8-D8 -> 66.43 | F8: =D8/C8 -> 0.86714 | G8: =SUMIFS('Raw Data'!K$2:K$81,'Raw Data'!B$2:B$81,$A8,'Raw Data'!S$2:S$81,"Stage 1") -> 288.43 | H8: =SUMIFS('Raw Data'!K$2:K$81,'Raw Data'!B$2:B$81,$A8,'Raw Data'!S$2:S$81,"Stage 2") -> 145.14 | I8: =SUMIFS('Raw Data'!K$2:K$81,'Raw Data'!B$2:B$81,$A8,'Raw Data'!S$2:S$81,"Stage 3") -> 0 | J8: =SUMIFS('Raw Data'!U$2:U$81,'Raw Data'!B$2:B$81,$A8) -> 15.98 | K8: =IF(D8=0,"-",J8/D8) -> 0.036856794 | L8: =IF(F8>=0.85,"🔴 CRITICAL",IF(F8>=0.7,"🟡 WARNING","🟢 NORMAL")) -> 🔴 CRITICAL
A9: Mirabank | B9: Serbia / Baltics / Europe | C9: 400 | D9: =SUMIFS('Raw Data'!K$2:K$81,'Raw Data'!B$2:B$81,$A9) -> 333.65 | E9: =C9-D9 -> 66.35 | F9: =D9/C9 -> 0.834125 | G9: =SUMIFS('Raw Data'!K$2:K$81,'Raw Data'!B$2:B$81,$A9,'Raw Data'!S$2:S$81,"Stage 1") -> 309.75 | H9: =SUMIFS('Raw Data'!K$2:K$81,'Raw Data'!B$2:B$81,$A9,'Raw Data'!S$2:S$81,"Stage 2") -> 23.9 | I9: =SUMIFS('Raw Data'!K$2:K$81,'Raw Data'!B$2:B$81,$A9,'Raw Data'!S$2:S$81,"Stage 3") -> 0 | J9: =SUMIFS('Raw Data'!U$2:U$81,'Raw Data'!B$2:B$81,$A9) -> 6.38 | K9: =IF(D9=0,"-",J9/D9) -> 0.019121834 | L9: =IF(F9>=0.85,"🔴 CRITICAL",IF(F9>=0.7,"🟡 WARNING","🟢 NORMAL")) -> 🟡 WARNING
A10: Lulo Bank | B10: Colombia (minimal TF) | C10: 50 | D10: =SUMIFS('Raw Data'!K$2:K$81,'Raw Data'!B$2:B$81,$A10) -> 32.69 | E10: =C10-D10 -> 17.31 | F10: =D10/C10 -> 0.6538 | G10: =SUMIFS('Raw Data'!K$2:K$81,'Raw Data'!B$2:B$81,$A10,'Raw Data'!S$2:S$81,"Stage 1") -> 32.69 | H10: =SUMIFS('Raw Data'!K$2:K$81,'Raw Data'!B$2:B$81,$A10,'Raw Data'!S$2:S$81,"Stage 2") -> 0 | I10: =SUMIFS('Raw Data'!K$2:K$81,'Raw Data'!B$2:B$81,$A10,'Raw Data'!S$2:S$81,"Stage 3") -> 0 | J10: =SUMIFS('Raw Data'!U$2:U$81,'Raw Data'!B$2:B$81,$A10) -> 0.22 | K10: =IF(D10=0,"-",J10/D10) -> 0.0067298868 | L10: =IF(F10>=0.85,"🔴 CRITICAL",IF(F10>=0.7,"🟡 WARNING","🟢 NORMAL")) -> 🟢 NORMAL
A11: GROUP TOTAL | C11: =SUM(C6:C10) -> 1950 | D11: =SUM(D6:D10) -> 1556.29 | E11: =SUM(E6:E10) -> 393.71 | F11: =D11/C11 -> 0.79809744 | G11: =SUM(G6:G10) -> 1375.08 | H11: =SUM(H6:H10) -> 177.62 | I11: =SUM(I6:I10) -> 3.59 | J11: =SUM(J6:J10) -> 34.86 | K11: =IF(D11=0,"-",J11/D11) -> 0.022399424 | L11: =IF(F11>=0.85,"🔴 CRITICAL",IF(F11>=0.7,"🟡 WARNING","🟢 NORMAL")) -> 🟡 WARNING

Sheet Product Mix
A1: PRODUCT MIX & TENOR ANALYSIS
A3: Product Type | B3: # Facilities | C3: Limit (USD mm) | D3: Outstanding (USD mm) | E3: % of Portfolio | F3: Avg Tenor | G3: Utilization | H3: Stage 2+3 % | I3: Avg Rating | J3: Watchlist #
A4: Import LC | B4: =COUNTIFS('Raw Data'!H$2:H$81,$A4) -> 24 | C4: =SUMIFS('Raw Data'!J$2:J$81,'Raw Data'!H$2:H$81,$A4) -> 713.44 | D4: =SUMIFS('Raw Data'!K$2:K$81,'Raw Data'!H$2:H$81,$A4) -> 592.3 | E4: =D4/SUM('Raw Data'!K$2:K$81) -> 0.3805846 | F4: =IF(B4=0,"-",AVERAGEIFS('Raw Data'!M$2:M$81,'Raw Data'!H$2:H$81,$A4)) -> 104.66667 | G4: =IF(C4=0,"-",D4/C4) -> 0.83020296 | H4: =IF(D4=0,"-",(SUMIFS('Raw Data'!K$2:K$81,'Raw Data'!H$2:H$81,$A4,'Raw Data'!S$2:S$81,"Stage 2")+SUMIFS('Raw Data'!K$2:K$81,'Raw Data'!H$2:H$81,$A4,'Raw Data'!S$2:S$81,"Stage 3"))/D4) -> 0.10859362 | I4: =IF(B4=0,"-",AVERAGEIFS('Raw Data'!P$2:P$81,'Raw Data'!H$2:H$81,$A4)) -> 4.75 | J4: =COUNTIFS('Raw Data'!H$2:H$81,$A4,'Raw Data'!Z$2:Z$81,"Yes") -> 3
A5: Export LC | B5: =COUNTIFS('Raw Data'!H$2:H$81,$A5) -> 10 | C5: =SUMIFS('Raw Data'!J$2:J$81,'Raw Data'!H$2:H$81,$A5) -> 394.33 | D5: =SUMIFS('Raw Data'!K$2:K$81,'Raw Data'!H$2:H$81,$A5) -> 311.11 | E5: =D5/SUM('Raw Data'!K$2:K$81) -> 0.1999049 | F5: =IF(B5=0,"-",AVERAGEIFS('Raw Data'!M$2:M$81,'Raw Data'!H$2:H$81,$A5)) -> 117.2 | G5: =IF(C5=0,"-",D5/C5) -> 0.78895849 | H5: =IF(D5=0,"-",(SUMIFS('Raw Data'!K$2:K$81,'Raw Data'!H$2:H$81,$A5,'Raw Data'!S$2:S$81,"Stage 2")+SUMIFS('Raw Data'!K$2:K$81,'Raw Data'!H$2:H$81,$A5,'Raw Data'!S$2:S$81,"Stage 3"))/D5) -> 0 | I5: =IF(B5=0,"-",AVERAGEIFS('Raw Data'!P$2:P$81,'Raw Data'!H$2:H$81,$A5)) -> 3.9 | J5: =COUNTIFS('Raw Data'!H$2:H$81,$A5,'Raw Data'!Z$2:Z$81,"Yes") -> 0
A6: Bank Guarantee - Performance | B6: =COUNTIFS('Raw Data'!H$2:H$81,$A6) -> 8 | C6: =SUMIFS('Raw Data'!J$2:J$81,'Raw Data'!H$2:H$81,$A6) -> 93.51 | D6: =SUMIFS('Raw Data'!K$2:K$81,'Raw Data'!H$2:H$81,$A6) -> 77.62 | E6: =D6/SUM('Raw Data'!K$2:K$81) -> 0.049875023 | F6: =IF(B6=0,"-",AVERAGEIFS('Raw Data'!M$2:M$81,'Raw Data'!H$2:H$81,$A6)) -> 248.5 | G6: =IF(C6=0,"-",D6/C6) -> 0.83007165 | H6: =IF(D6=0,"-",(SUMIFS('Raw Data'!K$2:K$81,'Raw Data'!H$2:H$81,$A6,'Raw Data'!S$2:S$81,"Stage 2")+SUMIFS('Raw Data'!K$2:K$81,'Raw Data'!H$2:H$81,$A6,'Raw Data'!S$2:S$81,"Stage 3"))/D6) -> 0 | I6: =IF(B6=0,"-",AVERAGEIFS('Raw Data'!P$2:P$81,'Raw Data'!H$2:H$81,$A6)) -> 5.25 | J6: =COUNTIFS('Raw Data'!H$2:H$81,$A6,'Raw Data'!Z$2:Z$81,"Yes") -> 0
A7: Bank Guarantee - Financial | B7: =COUNTIFS('Raw Data'!H$2:H$81,$A7) -> 4 | C7: =SUMIFS('Raw Data'!J$2:J$81,'Raw Data'!H$2:H$81,$A7) -> 75.2 | D7: =SUMIFS('Raw Data'!K$2:K$81,'Raw Data'!H$2:H$81,$A7) -> 68.91 | E7: =D7/SUM('Raw Data'!K$2:K$81) -> 0.04427838 | F7: =IF(B7=0,"-",AVERAGEIFS('Raw Data'!M$2:M$81,'Raw Data'!H$2:H$81,$A7)) -> 247 | G7: =IF(C7=0,"-",D7/C7) -> 0.91635638 | H7: =IF(D7=0,"-",(SUMIFS('Raw Data'!K$2:K$81,'Raw Data'!H$2:H$81,$A7,'Raw Data'!S$2:S$81,"Stage 2")+SUMIFS('Raw Data'!K$2:K$81,'Raw Data'!H$2:H$81,$A7,'Raw Data'!S$2:S$81,"Stage 3"))/D7) -> 0.60629807 | I7: =IF(B7=0,"-",AVERAGEIFS('Raw Data'!P$2:P$81,'Raw Data'!H$2:H$81,$A7)) -> 5.75 | J7: =COUNTIFS('Raw Data'!H$2:H$81,$A7,'Raw Data'!Z$2:Z$81,"Yes") -> 2
A8: Bank Guarantee - Bid Bond | B8: =COUNTIFS('Raw Data'!H$2:H$81,$A8) -> 2 | C8: =SUMIFS('Raw Data'!J$2:J$81,'Raw Data'!H$2:H$81,$A8) -> 21.2 | D8: =SUMIFS('Raw Data'!K$2:K$81,'Raw Data'!H$2:H$81,$A8) -> 13.56 | E8: =D8/SUM('Raw Data'!K$2:K$81) -> 0.0087130291 | F8: =IF(B8=0,"-",AVERAGEIFS('Raw Data'!M$2:M$81,'Raw Data'!H$2:H$81,$A8)) -> 76.5 | G8: =IF(C8=0,"-",D8/C8) -> 0.63962264 | H8: =IF(D8=0,"-",(SUMIFS('Raw Data'!K$2:K$81,'Raw Data'!H$2:H$81,$A8,'Raw Data'!S$2:S$81,"Stage 2")+SUMIFS('Raw Data'!K$2:K$81,'Raw Data'!H$2:H$81,$A8,'Raw Data'!S$2:S$81,"Stage 3"))/D8) -> 0 | I8: =IF(B8=0,"-",AVERAGEIFS('Raw Data'!P$2:P$81,'Raw Data'!H$2:H$81,$A8)) -> 4.5 | J8: =COUNTIFS('Raw Data'!H$2:H$81,$A8,'Raw Data'!Z$2:Z$81,"Yes") -> 0
A9: Trade Loan - Pre-Export | B9: =COUNTIFS('Raw Data'!H$2:H$81,$A9) -> 10 | C9: =SUMIFS('Raw Data'!J$2:J$81,'Raw Data'!H$2:H$81,$A9) -> 262.92 | D9: =SUMIFS('Raw Data'!K$2:K$81,'Raw Data'!H$2:H$81,$A9) -> 201.5 | E9: =D9/SUM('Raw Data'!K$2:K$81) -> 0.12947458 | F9: =IF(B9=0,"-",AVERAGEIFS('Raw Data'!M$2:M$81,'Raw Data'!H$2:H$81,$A9)) -> 102.1 | G9: =IF(C9=0,"-",D9/C9) -> 0.76639282 | H9: =IF(D9=0,"-",(SUMIFS('Raw Data'!K$2:K$81,'Raw Data'!H$2:H$81,$A9,'Raw Data'!S$2:S$81,"Stage 2")+SUMIFS('Raw Data'!K$2:K$81,'Raw Data'!H$2:H$81,$A9,'Raw Data'!S$2:S$81,"Stage 3"))/D9) -> 0.14188586 | I9: =IF(B9=0,"-",AVERAGEIFS('Raw Data'!P$2:P$81,'Raw Data'!H$2:H$81,$A9)) -> 4.8 | J9: =COUNTIFS('Raw Data'!H$2:H$81,$A9,'Raw Data'!Z$2:Z$81,"Yes") -> 1
A10: Trade Loan - Post-Import | B10: =COUNTIFS('Raw Data'!H$2:H$81,$A10) -> 7 | C10: =SUMIFS('Raw Data'!J$2:J$81,'Raw Data'!H$2:H$81,$A10) -> 153.39 | D10: =SUMIFS('Raw Data'!K$2:K$81,'Raw Data'!H$2:H$81,$A10) -> 133.64 | E10: =D10/SUM('Raw Data'!K$2:K$81) -> 0.085870885 | F10: =IF(B10=0,"-",AVERAGEIFS('Raw Data'!M$2:M$81,'Raw Data'!H$2:H$81,$A10)) -> 75.571429 | G10: =IF(C10=0,"-",D10/C10) -> 0.87124324 | H10: =IF(D10=0,"-",(SUMIFS('Raw Data'!K$2:K$81,'Raw Data'!H$2:H$81,$A10,'Raw Data'!S$2:S$81,"Stage 2")+SUMIFS('Raw Data'!K$2:K$81,'Raw Data'!H$2:H$81,$A10,'Raw Data'!S$2:S$81,"Stage 3"))/D10) -> 0.32123616 | I10: =IF(B10=0,"-",AVERAGEIFS('Raw Data'!P$2:P$81,'Raw Data'!H$2:H$81,$A10)) -> 6.1428571 | J10: =COUNTIFS('Raw Data'!H$2:H$81,$A10,'Raw Data'!Z$2:Z$81,"Yes") -> 2
A11: Supply Chain Finance | B11: =COUNTIFS('Raw Data'!H$2:H$81,$A11) -> 7 | C11: =SUMIFS('Raw Data'!J$2:J$81,'Raw Data'!H$2:H$81,$A11) -> 102.17 | D11: =SUMIFS('Raw Data'!K$2:K$81,'Raw Data'!H$2:H$81,$A11) -> 89.43 | E11: =D11/SUM('Raw Data'!K$2:K$81) -> 0.057463583 | F11: =IF(B11=0,"-",AVERAGEIFS('Raw Data'!M$2:M$81,'Raw Data'!H$2:H$81,$A11)) -> 76.428571 | G11: =IF(C11=0,"-",D11/C11) -> 0.87530586 | H11: =IF(D11=0,"-",(SUMIFS('Raw Data'!K$2:K$81,'Raw Data'!H$2:H$81,$A11,'Raw Data'!S$2:S$81,"Stage 2")+SUMIFS('Raw Data'!K$2:K$81,'Raw Data'!H$2:H$81,$A11,'Raw Data'!S$2:S$81,"Stage 3"))/D11) -> 0 | I11: =IF(B11=0,"-",AVERAGEIFS('Raw Data'!P$2:P$81,'Raw Data'!H$2:H$81,$A11)) -> 4.4285714 | J11: =COUNTIFS('Raw Data'!H$2:H$81,$A11,'Raw Data'!Z$2:Z$81,"Yes") -> 0
A12: Documentary Collection - D/P | B12: =COUNTIFS('Raw Data'!H$2:H$81,$A12) -> 3 | C12: =SUMIFS('Raw Data'!J$2:J$81,'Raw Data'!H$2:H$81,$A12) -> 37.1 | D12: =SUMIFS('Raw Data'!K$2:K$81,'Raw Data'!H$2:H$81,$A12) -> 29.14 | E12: =D12/SUM('Raw Data'!K$2:K$81) -> 0.018724017 | F12: =IF(B12=0,"-",AVERAGEIFS('Raw Data'!M$2:M$81,'Raw Data'!H$2:H$81,$A12)) -> 77 | G12: =IF(C12=0,"-",D12/C12) -> 0.78544474 | H12: =IF(D12=0,"-",(SUMIFS('Raw Data'!K$2:K$81,'Raw Data'!H$2:H$81,$A12,'Raw Data'!S$2:S$81,"Stage 2")+SUMIFS('Raw Data'!K$2:K$81,'Raw Data'!H$2:H$81,$A12,'Raw Data'!S$2:S$81,"Stage 3"))/D12) -> 0.12319835 | I12: =IF(B12=0,"-",AVERAGEIFS('Raw Data'!P$2:P$81,'Raw Data'!H$2:H$81,$A12)) -> 6 | J12: =COUNTIFS('Raw Data'!H$2:H$81,$A12,'Raw Data'!Z$2:Z$81,"Yes") -> 1
A13: Documentary Collection - D/A | B13: =COUNTIFS('Raw Data'!H$2:H$81,$A13) -> 2 | C13: =SUMIFS('Raw Data'!J$2:J$81,'Raw Data'!H$2:H$81,$A13) -> 20.3 | D13: =SUMIFS('Raw Data'!K$2:K$81,'Raw Data'!H$2:H$81,$A13) -> 18.56 | E13: =D13/SUM('Raw Data'!K$2:K$81) -> 0.011925798 | F13: =IF(B13=0,"-",AVERAGEIFS('Raw Data'!M$2:M$81,'Raw Data'!H$2:H$81,$A13)) -> 108.5 | G13: =IF(C13=0,"-",D13/C13) -> 0.91428571 | H13: =IF(D13=0,"-",(SUMIFS('Raw Data'!K$2:K$81,'Raw Data'!H$2:H$81,$A13,'Raw Data'!S$2:S$81,"Stage 2")+SUMIFS('Raw Data'!K$2:K$81,'Raw Data'!H$2:H$81,$A13,'Raw Data'!S$2:S$81,"Stage 3"))/D13) -> 0 | I13: =IF(B13=0,"-",AVERAGEIFS('Raw Data'!P$2:P$81,'Raw Data'!H$2:H$81,$A13)) -> 5.5 | J13: =COUNTIFS('Raw Data'!H$2:H$81,$A13,'Raw Data'!Z$2:Z$81,"Yes") -> 0
A14: Forfaiting | B14: =COUNTIFS('Raw Data'!H$2:H$81,$A14) -> 3 | C14: =SUMIFS('Raw Data'!J$2:J$81,'Raw Data'!H$2:H$81,$A14) -> 26.26 | D14: =SUMIFS('Raw Data'!K$2:K$81,'Raw Data'!H$2:H$81,$A14) -> 20.52 | E14: =D14/SUM('Raw Data'!K$2:K$81) -> 0.013185203 | F14: =IF(B14=0,"-",AVERAGEIFS('Raw Data'!M$2:M$81,'Raw Data'!H$2:H$81,$A14)) -> 221.33333 | G14: =IF(C14=0,"-",D14/C14) -> 0.7814166 | H14: =IF(D14=0,"-",(SUMIFS('Raw Data'!K$2:K$81,'Raw Data'!H$2:H$81,$A14,'Raw Data'!S$2:S$81,"Stage 2")+SUMIFS('Raw Data'!K$2:K$81,'Raw Data'!H$2:H$81,$A14,'Raw Data'!S$2:S$81,"Stage 3"))/D14) -> 0 | I14: =IF(B14=0,"-",AVERAGEIFS('Raw Data'!P$2:P$81,'Raw Data'!H$2:H$81,$A14)) -> 5.6666667 | J14: =COUNTIFS('Raw Data'!H$2:H$81,$A14,'Raw Data'!Z$2:Z$81,"Yes") -> 0
A15: TOTAL | B15: =SUM(B4:B14) -> 80 | C15: =SUM(C4:C14) -> 1899.82 | D15: =SUM(D4:D14) -> 1556.29 | E15: =SUM(E4:E14) -> 1 | F15: =AVERAGE('Raw Data'!M2:M81) -> 125.125 | G15: =D15/C15 -> 0.81917761 | H15: =(SUMIFS('Raw Data'!K2:K81,'Raw Data'!S2:S81,"Stage 2")+SUMIFS('Raw Data'!K2:K81,'Raw Data'!S2:S81,"Stage 3"))/SUM('Raw Data'!K2:K81) -> 0.11643717 | I15: =AVERAGE('Raw Data'!P2:P81) -> 4.9375 | J15: =SUM(J4:J14) -> 9

Sheet Asset Quality
A1: ASSET QUALITY & IFRS 9 STAGING DASHBOARD
A2: IFRS 9 stage distribution, ECL coverage, and rating migration by entity
A4: 1. IFRS 9 STAGING BY ENTITY
A5: Entity | B5: Stage 1 (#) | C5: Stage 1 (USD mm) | D5: Stage 2 (#) | E5: Stage 2 (USD mm) | F5: Stage 3 (#) | G5: Stage 3 (USD mm) | H5: Stage 2+3 % | I5: Provision Coverage % | J5: RAG
A6: Samman Capital | B6: =COUNTIFS('Raw Data'!B$2:B$81,$A6,'Raw Data'!S$2:S$81,"Stage 1") -> 28 | C6: =SUMIFS('Raw Data'!K$2:K$81,'Raw Data'!B$2:B$81,$A6,'Raw Data'!S$2:S$81,"Stage 1") -> 556.02 | D6: =COUNTIFS('Raw Data'!B$2:B$81,$A6,'Raw Data'!S$2:S$81,"Stage 2") -> 1 | E6: =SUMIFS('Raw Data'!K$2:K$81,'Raw Data'!B$2:B$81,$A6,'Raw Data'!S$2:S$81,"Stage 2") -> 2.07 | F6: =COUNTIFS('Raw Data'!B$2:B$81,$A6,'Raw Data'!S$2:S$81,"Stage 3") -> 0 | G6: =SUMIFS('Raw Data'!K$2:K$81,'Raw Data'!B$2:B$81,$A6,'Raw Data'!S$2:S$81,"Stage 3") -> 0 | H6: =IF(SUMIFS('Raw Data'!K$2:K$81,'Raw Data'!B$2:B$81,$A6)=0,"-",(E6+G6)/SUMIFS('Raw Data'!K$2:K$81,'Raw Data'!B$2:B$81,$A6)) -> 0.0037090792 | I6: =IF(SUMIFS('Raw Data'!K$2:K$81,'Raw Data'!B$2:B$81,$A6)=0,"-",SUMIFS('Raw Data'!U$2:U$81,'Raw Data'!B$2:B$81,$A6)/SUMIFS('Raw Data'!K$2:K$81,'Raw Data'!B$2:B$81,$A6)) -> 0.01356412 | J6: =IF(H6="-","🟢 Green",IF(H6>=0.15,"🔴 Red",IF(H6>=0.08,"🟡 Amber","🟢 Green"))) -> 🟢 Green
A7: First Women Bank Ltd (FWBL) | B7: =COUNTIFS('Raw Data'!B$2:B$81,$A7,'Raw Data'!S$2:S$81,"Stage 1") -> 10 | C7: =SUMIFS('Raw Data'!K$2:K$81,'Raw Data'!B$2:B$81,$A7,'Raw Data'!S$2:S$81,"Stage 1") -> 188.19 | D7: =COUNTIFS('Raw Data'!B$2:B$81,$A7,'Raw Data'!S$2:S$81,"Stage 2") -> 1 | E7: =SUMIFS('Raw Data'!K$2:K$81,'Raw Data'!B$2:B$81,$A7,'Raw Data'!S$2:S$81,"Stage 2") -> 6.51 | F7: =COUNTIFS('Raw Data'!B$2:B$81,$A7,'Raw Data'!S$2:S$81,"Stage 3") -> 1 | G7: =SUMIFS('Raw Data'!K$2:K$81,'Raw Data'!B$2:B$81,$A7,'Raw Data'!S$2:S$81,"Stage 3") -> 3.59 | H7: =IF(SUMIFS('Raw Data'!K$2:K$81,'Raw Data'!B$2:B$81,$A7)=0,"-",(E7+G7)/SUMIFS('Raw Data'!K$2:K$81,'Raw Data'!B$2:B$81,$A7)) -> 0.050935499 | I7: =IF(SUMIFS('Raw Data'!K$2:K$81,'Raw Data'!B$2:B$81,$A7)=0,"-",SUMIFS('Raw Data'!U$2:U$81,'Raw Data'!B$2:B$81,$A7)/SUMIFS('Raw Data'!K$2:K$81,'Raw Data'!B$2:B$81,$A7)) -> 0.023753089 | J7: =IF(H7="-","🟢 Green",IF(H7>=0.15,"🔴 Red",IF(H7>=0.08,"🟡 Amber","🟢 Green"))) -> 🟢 Green
A8: Beltone | B8: =COUNTIFS('Raw Data'!B$2:B$81,$A8,'Raw Data'!S$2:S$81,"Stage 1") -> 14 | C8: =SUMIFS('Raw Data'!K$2:K$81,'Raw Data'!B$2:B$81,$A8,'Raw Data'!S$2:S$81,"Stage 1") -> 288.43 | D8: =COUNTIFS('Raw Data'!B$2:B$81,$A8,'Raw Data'!S$2:S$81,"Stage 2") -> 5 | E8: =SUMIFS('Raw Data'!K$2:K$81,'Raw Data'!B$2:B$81,$A8,'Raw Data'!S$2:S$81,"Stage 2") -> 145.14 | F8: =COUNTIFS('Raw Data'!B$2:B$81,$A8,'Raw Data'!S$2:S$81,"Stage 3") -> 0 | G8: =SUMIFS('Raw Data'!K$2:K$81,'Raw Data'!B$2:B$81,$A8,'Raw Data'!S$2:S$81,"Stage 3") -> 0 | H8: =IF(SUMIFS('Raw Data'!K$2:K$81,'Raw Data'!B$2:B$81,$A8)=0,"-",(E8+G8)/SUMIFS('Raw Data'!K$2:K$81,'Raw Data'!B$2:B$81,$A8)) -> 0.33475563 | I8: =IF(SUMIFS('Raw Data'!K$2:K$81,'Raw Data'!B$2:B$81,$A8)=0,"-",SUMIFS('Raw Data'!U$2:U$81,'Raw Data'!B$2:B$81,$A8)/SUMIFS('Raw Data'!K$2:K$81,'Raw Data'!B$2:B$81,$A8)) -> 0.036856794 | J8: =IF(H8="-","🟢 Green",IF(H8>=0.15,"🔴 Red",IF(H8>=0.08,"🟡 Amber","🟢 Green"))) -> 🔴 Red
A9: Mirabank | B9: =COUNTIFS('Raw Data'!B$2:B$81,$A9,'Raw Data'!S$2:S$81,"Stage 1") -> 17 | C9: =SUMIFS('Raw Data'!K$2:K$81,'Raw Data'!B$2:B$81,$A9,'Raw Data'!S$2:S$81,"Stage 1") -> 309.75 | D9: =COUNTIFS('Raw Data'!B$2:B$81,$A9,'Raw Data'!S$2:S$81,"Stage 2") -> 1 | E9: =SUMIFS('Raw Data'!K$2:K$81,'Raw Data'!B$2:B$81,$A9,'Raw Data'!S$2:S$81,"Stage 2") -> 23.9 | F9: =COUNTIFS('Raw Data'!B$2:B$81,$A9,'Raw Data'!S$2:S$81,"Stage 3") -> 0 | G9: =SUMIFS('Raw Data'!K$2:K$81,'Raw Data'!B$2:B$81,$A9,'Raw Data'!S$2:S$81,"Stage 3") -> 0 | H9: =IF(SUMIFS('Raw Data'!K$2:K$81,'Raw Data'!B$2:B$81,$A9)=0,"-",(E9+G9)/SUMIFS('Raw Data'!K$2:K$81,'Raw Data'!B$2:B$81,$A9)) -> 0.07163195 | I9: =IF(SUMIFS('Raw Data'!K$2:K$81,'Raw Data'!B$2:B$81,$A9)=0,"-",SUMIFS('Raw Data'!U$2:U$81,'Raw Data'!B$2:B$81,$A9)/SUMIFS('Raw Data'!K$2:K$81,'Raw Data'!B$2:B$81,$A9)) -> 0.019121834 | J9: =IF(H9="-","🟢 Green",IF(H9>=0.15,"🔴 Red",IF(H9>=0.08,"🟡 Amber","🟢 Green"))) -> 🟢 Green
A10: Lulo Bank | B10: =COUNTIFS('Raw Data'!B$2:B$81,$A10,'Raw Data'!S$2:S$81,"Stage 1") -> 2 | C10: =SUMIFS('Raw Data'!K$2:K$81,'Raw Data'!B$2:B$81,$A10,'Raw Data'!S$2:S$81,"Stage 1") -> 32.69 | D10: =COUNTIFS('Raw Data'!B$2:B$81,$A10,'Raw Data'!S$2:S$81,"Stage 2") -> 0 | E10: =SUMIFS('Raw Data'!K$2:K$81,'Raw Data'!B$2:B$81,$A10,'Raw Data'!S$2:S$81,"Stage 2") -> 0 | F10: =COUNTIFS('Raw Data'!B$2:B$81,$A10,'Raw Data'!S$2:S$81,"Stage 3") -> 0 | G10: =SUMIFS('Raw Data'!K$2:K$81,'Raw Data'!B$2:B$81,$A10,'Raw Data'!S$2:S$81,"Stage 3") -> 0 | H10: =IF(SUMIFS('Raw Data'!K$2:K$81,'Raw Data'!B$2:B$81,$A10)=0,"-",(E10+G10)/SUMIFS('Raw Data'!K$2:K$81,'Raw Data'!B$2:B$81,$A10)) -> 0 | I10: =IF(SUMIFS('Raw Data'!K$2:K$81,'Raw Data'!B$2:B$81,$A10)=0,"-",SUMIFS('Raw Data'!U$2:U$81,'Raw Data'!B$2:B$81,$A10)/SUMIFS('Raw Data'!K$2:K$81,'Raw Data'!B$2:B$81,$A10)) -> 0.0067298868 | J10: =IF(H10="-","🟢 Green",IF(H10>=0.15,"🔴 Red",IF(H10>=0.08,"🟡 Amber","🟢 Green"))) -> 🟢 Green
A11: GROUP TOTAL | B11: =SUM(B6:B10) -> 71 | C11: =SUM(C6:C10) -> 1375.08 | D11: =SUM(D6:D10) -> 8 | E11: =SUM(E6:E10) -> 177.62 | F11: =SUM(F6:F10) -> 1 | G11: =SUM(G6:G10) -> 3.59 | H11: =(E11+G11)/(C11+E11+G11) -> 0.11643717 | I11: =SUM('Raw Data'!U2:U81)/SUM('Raw Data'!K2:K81) -> 0.022399424
A13: 2. INTERNAL RATING DISTRIBUTION
A14: Rating Bucket | B14: Grade | C14: # Facilities | D14: Outstanding (USD mm) | E14: % of Portfolio | F14: Avg Provision Rate
A15: 1-2 (Minimal Risk) | B15: IG Prime | C15: =COUNTIFS('Raw Data'!P$2:P$81,"<="&2) -> 5 | D15: {=SUMPRODUCT(('Raw Data'!P$2:P$81<=2)*('Raw Data'!K$2:K$81))} -> 94.11 | E15: =D15/SUM('Raw Data'!K$2:K$81) -> 0.060470735 | F15: =IF(C15=0,"-",AVERAGEIFS('Raw Data'!T$2:T$81,'Raw Data'!P$2:P$81,"<="&2)) -> 0.01232
A16: 3-4 (Low Risk) | B16: IG | C16: =COUNTIFS('Raw Data'!P$2:P$81,">"&2,'Raw Data'!P$2:P$81,"<="&4) -> 30 | D16: {=SUMPRODUCT(('Raw Data'!P$2:P$81>2)*('Raw Data'!P$2:P$81<=4)*('Raw Data'!K$2:K$81))} -> 614.7 | E16: =D16/SUM('Raw Data'!K$2:K$81) -> 0.3949778 | F16: =IF(C16=0,"-",AVERAGEIFS('Raw Data'!T$2:T$81,'Raw Data'!P$2:P$81,">"&2,'Raw Data'!P$2:P$81,"<="&4)) -> 0.01347
A17: 5-6 (Moderate Risk) | B17: Sub-IG | C17: =COUNTIFS('Raw Data'!P$2:P$81,">"&4,'Raw Data'!P$2:P$81,"<="&6) -> 30 | D17: {=SUMPRODUCT(('Raw Data'!P$2:P$81>4)*('Raw Data'!P$2:P$81<=6)*('Raw Data'!K$2:K$81))} -> 585.08 | E17: =D17/SUM('Raw Data'!K$2:K$81) -> 0.37594536 | F17: =IF(C17=0,"-",AVERAGEIFS('Raw Data'!T$2:T$81,'Raw Data'!P$2:P$81,">"&4,'Raw Data'!P$2:P$81,"<="&6)) -> 0.011663333
A18: 7-8 (High Risk) | B18: Speculative | C18: =COUNTIFS('Raw Data'!P$2:P$81,">"&6,'Raw Data'!P$2:P$81,"<="&8) -> 12 | D18: {=SUMPRODUCT(('Raw Data'!P$2:P$81>6)*('Raw Data'!P$2:P$81<=8)*('Raw Data'!K$2:K$81))} -> 193.8 | E18: =D18/SUM('Raw Data'!K$2:K$81) -> 0.12452692 | F18: =IF(C18=0,"-",AVERAGEIFS('Raw Data'!T$2:T$81,'Raw Data'!P$2:P$81,">"&6,'Raw Data'!P$2:P$81,"<="&8)) -> 0.056908333
A19: 9-10 (Very High / Default) | B19: Default | C19: =COUNTIFS('Raw Data'!P$2:P$81,">"&8) -> 3 | D19: {=SUMPRODUCT(('Raw Data'!P$2:P$81>8)*('Raw Data'!K$2:K$81))} -> 68.6 | E19: =D19/SUM('Raw Data'!K$2:K$81) -> 0.044079188 | F19: =IF(C19=0,"-",AVERAGEIFS('Raw Data'!T$2:T$81,'Raw Data'!P$2:P$81,">"&8)) -> 0.1838
A20: TOTAL | C20: =SUM(C15:C19) -> 80 | D20: =SUM(D15:D19) -> 1556.29 | E20: =SUM(E15:E19) -> 1 | F20: =AVERAGE('Raw Data'!T2:T81) -> 0.02562375

Sheet Concentrations
A1: CONCENTRATION & EXPOSURE ANALYSIS
A2: Top obligor, sector, and geographic concentration risk monitoring
A4: 1. TOP 20 OBLIGOR CONCENTRATION
A5: Rank | B5: Obligor Name | C5: Entity | D5: # Facilities | E5: Outstanding (USD mm) | F5: % of Portfolio | G5: Internal Rating | H5: Watchlist
A6: 1 | B6: Al Habtoor Group | C6: Multi-entity | D6: =COUNTIF('Raw Data'!C$2:C$81,B6) -> 3 | E6: =SUMIF('Raw Data'!C$2:C$81,B6,'Raw Data'!K$2:K$81) -> 40.99 | F6: =E6/SUM('Raw Data'!K$2:K$81) -> 0.026338279 | G6: =AVERAGEIF('Raw Data'!C$2:C$81,B6,'Raw Data'!P$2:P$81) -> 4 | H6: =COUNTIFS('Raw Data'!C$2:C$81,B6,'Raw Data'!Z$2:Z$81,"Yes") -> 0
A7: 2 | B7: Emaar Properties | C7: Multi-entity | D7: =COUNTIF('Raw Data'!C$2:C$81,B7) -> 3 | E7: =SUMIF('Raw Data'!C$2:C$81,B7,'Raw Data'!K$2:K$81) -> 52.04 | F7: =E7/SUM('Raw Data'!K$2:K$81) -> 0.033438498 | G7: =AVERAGEIF('Raw Data'!C$2:C$81,B7,'Raw Data'!P$2:P$81) -> 5.3333333 | H7: =COUNTIFS('Raw Data'!C$2:C$81,B7,'Raw Data'!Z$2:Z$81,"Yes") -> 0
A8: 3 | B8: Reliance Industries | C8: Samman Capital | D8: =COUNTIF('Raw Data'!C$2:C$81,B8) -> 2 | E8: =SUMIF('Raw Data'!C$2:C$81,B8,'Raw Data'!K$2:K$81) -> 31.48 | F8: =E8/SUM('Raw Data'!K$2:K$81) -> 0.020227593 | G8: =AVERAGEIF('Raw Data'!C$2:C$81,B8,'Raw Data'!P$2:P$81) -> 4 | H8: =COUNTIFS('Raw Data'!C$2:C$81,B8,'Raw Data'!Z$2:Z$81,"Yes") -> 0
A9: 4 | B9: Gulf Petrochem | C9: Multi-entity | D9: =COUNTIF('Raw Data'!C$2:C$81,B9) -> 2 | E9: =SUMIF('Raw Data'!C$2:C$81,B9,'Raw Data'!K$2:K$81) -> 38.33 | F9: =E9/SUM('Raw Data'!K$2:K$81) -> 0.024629086 | G9: =AVERAGEIF('Raw Data'!C$2:C$81,B9,'Raw Data'!P$2:P$81) -> 5.5 | H9: =COUNTIFS('Raw Data'!C$2:C$81,B9,'Raw Data'!Z$2:Z$81,"Yes") -> 0
A10: 5 | B10: Al Ghurair Resources | C10: Multi-entity | D10: =COUNTIF('Raw Data'!C$2:C$81,B10) -> 2 | E10: =SUMIF('Raw Data'!C$2:C$81,B10,'Raw Data'!K$2:K$81) -> 55.22 | F10: =E10/SUM('Raw Data'!K$2:K$81) -> 0.035481819 | G10: =AVERAGEIF('Raw Data'!C$2:C$81,B10,'Raw Data'!P$2:P$81) -> 6.5 | H10: =COUNTIFS('Raw Data'!C$2:C$81,B10,'Raw Data'!Z$2:Z$81,"Yes") -> 0
A11: 6 | B11: National Marine Dredging | C11: Samman Capital | D11: =COUNTIF('Raw Data'!C$2:C$81,B11) -> 2 | E11: =SUMIF('Raw Data'!C$2:C$81,B11,'Raw Data'!K$2:K$81) -> 31.76 | F11: =E11/SUM('Raw Data'!K$2:K$81) -> 0.020407508 | G11: =AVERAGEIF('Raw Data'!C$2:C$81,B11,'Raw Data'!P$2:P$81) -> 3 | H11: =COUNTIFS('Raw Data'!C$2:C$81,B11,'Raw Data'!Z$2:Z$81,"Yes") -> 0
A12: 7 | B12: ADNOC Distribution | C12: Multi-entity | D12: =COUNTIF('Raw Data'!C$2:C$81,B12) -> 2 | E12: =SUMIF('Raw Data'!C$2:C$81,B12,'Raw Data'!K$2:K$81) -> 53.12 | F12: =E12/SUM('Raw Data'!K$2:K$81) -> 0.034132456 | G12: =AVERAGEIF('Raw Data'!C$2:C$81,B12,'Raw Data'!P$2:P$81) -> 4 | H12: =COUNTIFS('Raw Data'!C$2:C$81,B12,'Raw Data'!Z$2:Z$81,"Yes") -> 0
A13: 8 | B13: Tata Steel Trading | C13: Samman Capital | D13: =COUNTIF('Raw Data'!C$2:C$81,B13) -> 2 | E13: =SUMIF('Raw Data'!C$2:C$81,B13,'Raw Data'!K$2:K$81) -> 8.47 | F13: =E13/SUM('Raw Data'!K$2:K$81) -> 0.0054424304 | G13: =AVERAGEIF('Raw Data'!C$2:C$81,B13,'Raw Data'!P$2:P$81) -> 5 | H13: =COUNTIFS('Raw Data'!C$2:C$81,B13,'Raw Data'!Z$2:Z$81,"Yes") -> 0
A14: 9 | B14: Mashreq Corporate | C14: Multi-entity | D14: =COUNTIF('Raw Data'!C$2:C$81,B14) -> 2 | E14: =SUMIF('Raw Data'!C$2:C$81,B14,'Raw Data'!K$2:K$81) -> 21.6 | F14: =E14/SUM('Raw Data'!K$2:K$81) -> 0.013879161 | G14: =AVERAGEIF('Raw Data'!C$2:C$81,B14,'Raw Data'!P$2:P$81) -> 3 | H14: =COUNTIFS('Raw Data'!C$2:C$81,B14,'Raw Data'!Z$2:Z$81,"Yes") -> 0
A15: 10 | B15: Adani Enterprises | C15: Samman Capital | D15: =COUNTIF('Raw Data'!C$2:C$81,B15) -> 2 | E15: =SUMIF('Raw Data'!C$2:C$81,B15,'Raw Data'!K$2:K$81) -> 27.88 | F15: =E15/SUM('Raw Data'!K$2:K$81) -> 0.017914399 | G15: =AVERAGEIF('Raw Data'!C$2:C$81,B15,'Raw Data'!P$2:P$81) -> 5.5 | H15: =COUNTIFS('Raw Data'!C$2:C$81,B15,'Raw Data'!Z$2:Z$81,"Yes") -> 0
A16: Top 10 Total | D16: =SUM(D6:D15) -> 22 | E16: =SUM(E6:E15) -> 360.89 | F16: =SUM(F6:F15) -> 0.23189123
A18: 2. SECTOR CONCENTRATION
A19: Sector | B19: # Facilities | C19: Outstanding (USD mm) | D19: % of Portfolio | E19: Limit (25%) | F19: RAG
A20: Oil & Gas | B20: =COUNTIF('Raw Data'!F$2:F$81,$A20) -> 18 | C20: =SUMIF('Raw Data'!F$2:F$81,$A20,'Raw Data'!K$2:K$81) -> 398.25 | D20: =C20/SUM('Raw Data'!K$2:K$81) -> 0.25589704 | E20: =SUM('Raw Data'!K$2:K$81)*0.25 -> 389.0725 | F20: =IF(D20>0.25,"🔴 Breach",IF(D20>0.2,"🟡 Warning","🟢 OK")) -> 🔴 Breach
A21: Agriculture & Food | B21: =COUNTIF('Raw Data'!F$2:F$81,$A21) -> 16 | C21: =SUMIF('Raw Data'!F$2:F$81,$A21,'Raw Data'!K$2:K$81) -> 306.64 | D21: =C21/SUM('Raw Data'!K$2:K$81) -> 0.19703269 | E21: =SUM('Raw Data'!K$2:K$81)*0.25 -> 389.0725 | F21: =IF(D21>0.25,"🔴 Breach",IF(D21>0.2,"🟡 Warning","🟢 OK")) -> 🟢 OK
A22: Metals & Mining | B22: =COUNTIF('Raw Data'!F$2:F$81,$A22) -> 10 | C22: =SUMIF('Raw Data'!F$2:F$81,$A22,'Raw Data'!K$2:K$81) -> 232.97 | D22: =C22/SUM('Raw Data'!K$2:K$81) -> 0.14969575 | E22: =SUM('Raw Data'!K$2:K$81)*0.25 -> 389.0725 | F22: =IF(D22>0.25,"🔴 Breach",IF(D22>0.2,"🟡 Warning","🟢 OK")) -> 🟢 OK
A23: Electronics & Technology | B23: =COUNTIF('Raw Data'!F$2:F$81,$A23) -> 8 | C23: =SUMIF('Raw Data'!F$2:F$81,$A23,'Raw Data'!K$2:K$81) -> 111.69 | D23: =C23/SUM('Raw Data'!K$2:K$81) -> 0.07176683 | E23: =SUM('Raw Data'!K$2:K$81)*0.25 -> 389.0725 | F23: =IF(D23>0.25,"🔴 Breach",IF(D23>0.2,"🟡 Warning","🟢 OK")) -> 🟢 OK
A24: Petrochemicals | B24: =COUNTIF('Raw Data'!F$2:F$81,$A24) -> 6 | C24: =SUMIF('Raw Data'!F$2:F$81,$A24,'Raw Data'!K$2:K$81) -> 145.17 | D24: =C24/SUM('Raw Data'!K$2:K$81) -> 0.09327953 | E24: =SUM('Raw Data'!K$2:K$81)*0.25 -> 389.0725 | F24: =IF(D24>0.25,"🔴 Breach",IF(D24>0.2,"🟡 Warning","🟢 OK")) -> 🟢 OK
A25: Construction & Real Estate | B25: =COUNTIF('Raw Data'!F$2:F$81,$A25) -> 6 | C25: =SUMIF('Raw Data'!F$2:F$81,$A25,'Raw Data'!K$2:K$81) -> 104.86 | D25: =C25/SUM('Raw Data'!K$2:K$81) -> 0.067378188 | E25: =SUM('Raw Data'!K$2:K$81)*0.25 -> 389.0725 | F25: =IF(D25>0.25,"🔴 Breach",IF(D25>0.2,"🟡 Warning","🟢 OK")) -> 🟢 OK
A26: Manufacturing | B26: =COUNTIF('Raw Data'!F$2:F$81,$A26) -> 3 | C26: =SUMIF('Raw Data'!F$2:F$81,$A26,'Raw Data'!K$2:K$81) -> 77.95 | D26: =C26/SUM('Raw Data'!K$2:K$81) -> 0.050087066 | E26: =SUM('Raw Data'!K$2:K$81)*0.25 -> 389.0725 | F26: =IF(D26>0.25,"🔴 Breach",IF(D26>0.2,"🟡 Warning","🟢 OK")) -> 🟢 OK
A27: Consumer Goods | B27: =COUNTIF('Raw Data'!F$2:F$81,$A27) -> 3 | C27: =SUMIF('Raw Data'!F$2:F$81,$A27,'Raw Data'!K$2:K$81) -> 83.24 | D27: =C27/SUM('Raw Data'!K$2:K$81) -> 0.053486175 | E27: =SUM('Raw Data'!K$2:K$81)*0.25 -> 389.0725 | F27: =IF(D27>0.25,"🔴 Breach",IF(D27>0.2,"🟡 Warning","🟢 OK")) -> 🟢 OK
A28: Utilities & Power | B28: =COUNTIF('Raw Data'!F$2:F$81,$A28) -> 3 | C28: =SUMIF('Raw Data'!F$2:F$81,$A28,'Raw Data'!K$2:K$81) -> 15.02 | D28: =C28/SUM('Raw Data'!K$2:K$81) -> 0.0096511576 | E28: =SUM('Raw Data'!K$2:K$81)*0.25 -> 389.0725 | F28: =IF(D28>0.25,"🔴 Breach",IF(D28>0.2,"🟡 Warning","🟢 OK")) -> 🟢 OK
A29: Textiles & Apparel | B29: =COUNTIF('Raw Data'!F$2:F$81,$A29) -> 3 | C29: =SUMIF('Raw Data'!F$2:F$81,$A29,'Raw Data'!K$2:K$81) -> 17.19 | D29: =C29/SUM('Raw Data'!K$2:K$81) -> 0.011045499 | E29: =SUM('Raw Data'!K$2:K$81)*0.25 -> 389.0725 | F29: =IF(D29>0.25,"🔴 Breach",IF(D29>0.2,"🟡 Warning","🟢 OK")) -> 🟢 OK
A30: Shipping & Logistics | B30: =COUNTIF('Raw Data'!F$2:F$81,$A30) -> 2 | C30: =SUMIF('Raw Data'!F$2:F$81,$A30,'Raw Data'!K$2:K$81) -> 44.96 | D30: =C30/SUM('Raw Data'!K$2:K$81) -> 0.028889217 | E30: =SUM('Raw Data'!K$2:K$81)*0.25 -> 389.0725 | F30: =IF(D30>0.25,"🔴 Breach",IF(D30>0.2,"🟡 Warning","🟢 OK")) -> 🟢 OK
A31: Pharmaceuticals | B31: =COUNTIF('Raw Data'!F$2:F$81,$A31) -> 1 | C31: =SUMIF('Raw Data'!F$2:F$81,$A31,'Raw Data'!K$2:K$81) -> 11.38 | D31: =C31/SUM('Raw Data'!K$2:K$81) -> 0.0073122619 | E31: =SUM('Raw Data'!K$2:K$81)*0.25 -> 389.0725 | F31: =IF(D31>0.25,"🔴 Breach",IF(D31>0.2,"🟡 Warning","🟢 OK")) -> 🟢 OK
A32: Automotive | B32: =COUNTIF('Raw Data'!F$2:F$81,$A32) -> 1 | C32: =SUMIF('Raw Data'!F$2:F$81,$A32,'Raw Data'!K$2:K$81) -> 6.97 | D32: =C32/SUM('Raw Data'!K$2:K$81) -> 0.0044785997 | E32: =SUM('Raw Data'!K$2:K$81)*0.25 -> 389.0725 | F32: =IF(D32>0.25,"🔴 Breach",IF(D32>0.2,"🟡 Warning","🟢 OK")) -> 🟢 OK
A33: TOTAL | B33: =SUM(B20:B32) -> 80 | C33: =SUM(C20:C32) -> 1556.29 | D33: =SUM(D20:D32) -> 1

Sheet Collections & Efficiency
A1: COLLECTIONS, EFFICIENCY & PERFORMANCE MONITORING
A2: Collection efficiency, overdue aging, maturity profile, and recovery metrics by entity
A4: 1. COLLECTION EFFICIENCY BY ENTITY
A5: Entity | B5: Collection Efficiency Ratio | C5: Overdue Ratio | D5: Avg DPD (Overdue) | E5: Recovery Rate (Stage 3) | F5: Rollover Rate | G5: Provision / Outstanding | H5: Efficiency RAG
A6: Samman Capital | B6: {=1-SUMPRODUCT(('Raw Data'!B$2:B$81=$A6)*('Raw Data'!R$2:R$81>0)*('Raw Data'!K$2:K$81))/SUMIFS('Raw Data'!K$2:K$81,'Raw Data'!B$2:B$81,$A6)} -> 0.99629092 | C6: {=IF(SUMIFS('Raw Data'!K$2:K$81,'Raw Data'!B$2:B$81,$A6)=0,"-",SUMPRODUCT(('Raw Data'!B$2:B$81=$A6)*('Raw Data'!R$2:R$81>0)*('Raw Data'!K$2:K$81))/SUMIFS('Raw Data'!K$2:K$81,'Raw Data'!B$2:B$81,$A6))} -> 0.0037090792 | D6: =IF(COUNTIFS('Raw Data'!B$2:B$81,$A6,'Raw Data'!R$2:R$81,">0")=0,"N/A",AVERAGEIFS('Raw Data'!R$2:R$81,'Raw Data'!B$2:B$81,$A6,'Raw Data'!R$2:R$81,">0")) -> 19 | E6: =IF(SUMIFS('Raw Data'!K$2:K$81,'Raw Data'!B$2:B$81,$A6,'Raw Data'!S$2:S$81,"Stage 3")=0,"N/A",SUMIFS('Raw Data'!U$2:U$81,'Raw Data'!B$2:B$81,$A6,'Raw Data'!S$2:S$81,"Stage 3")/SUMIFS('Raw Data'!K$2:K$81,'Raw Data'!B$2:B$81,$A6,'Raw Data'!S$2:S$81,"Stage 3")) -> N/A | F6: 0.82 | G6: =SUMIFS('Raw Data'!U$2:U$81,'Raw Data'!B$2:B$81,$A6)/SUMIFS('Raw Data'!K$2:K$81,'Raw Data'!B$2:B$81,$A6) -> 0.01356412 | H6: =IF(C6<=0.05,"🟢 Green",IF(C6<=0.1,"🟡 Amber","🔴 Red")) -> 🟢 Green
A7: First Women Bank Ltd (FWBL) | B7: {=1-SUMPRODUCT(('Raw Data'!B$2:B$81=$A7)*('Raw Data'!R$2:R$81>0)*('Raw Data'!K$2:K$81))/SUMIFS('Raw Data'!K$2:K$81,'Raw Data'!B$2:B$81,$A7)} -> 0.9490645 | C7: {=IF(SUMIFS('Raw Data'!K$2:K$81,'Raw Data'!B$2:B$81,$A7)=0,"-",SUMPRODUCT(('Raw Data'!B$2:B$81=$A7)*('Raw Data'!R$2:R$81>0)*('Raw Data'!K$2:K$81))/SUMIFS('Raw Data'!K$2:K$81,'Raw Data'!B$2:B$81,$A7))} -> 0.050935499 | D7: =IF(COUNTIFS('Raw Data'!B$2:B$81,$A7,'Raw Data'!R$2:R$81,">0")=0,"N/A",AVERAGEIFS('Raw Data'!R$2:R$81,'Raw Data'!B$2:B$81,$A7,'Raw Data'!R$2:R$81,">0")) -> 58.5 | E7: =IF(SUMIFS('Raw Data'!K$2:K$81,'Raw Data'!B$2:B$81,$A7,'Raw Data'!S$2:S$81,"Stage 3")=0,"N/A",SUMIFS('Raw Data'!U$2:U$81,'Raw Data'!B$2:B$81,$A7,'Raw Data'!S$2:S$81,"Stage 3")/SUMIFS('Raw Data'!K$2:K$81,'Raw Data'!B$2:B$81,$A7,'Raw Data'!S$2:S$81,"Stage 3")) -> 0.39275766 | F7: 0.78 | G7: =SUMIFS('Raw Data'!U$2:U$81,'Raw Data'!B$2:B$81,$A7)/SUMIFS('Raw Data'!K$2:K$81,'Raw Data'!B$2:B$81,$A7) -> 0.023753089 | H7: =IF(C7<=0.05,"🟢 Green",IF(C7<=0.1,"🟡 Amber","🔴 Red")) -> 🟡 Amber
A8: Beltone | B8: {=1-SUMPRODUCT(('Raw Data'!B$2:B$81=$A8)*('Raw Data'!R$2:R$81>0)*('Raw Data'!K$2:K$81))/SUMIFS('Raw Data'!K$2:K$81,'Raw Data'!B$2:B$81,$A8)} -> 0.78893835 | C8: {=IF(SUMIFS('Raw Data'!K$2:K$81,'Raw Data'!B$2:B$81,$A8)=0,"-",SUMPRODUCT(('Raw Data'!B$2:B$81=$A8)*('Raw Data'!R$2:R$81>0)*('Raw Data'!K$2:K$81))/SUMIFS('Raw Data'!K$2:K$81,'Raw Data'!B$2:B$81,$A8))} -> 0.21106165 | D8: =IF(COUNTIFS('Raw Data'!B$2:B$81,$A8,'Raw Data'!R$2:R$81,">0")=0,"N/A",AVERAGEIFS('Raw Data'!R$2:R$81,'Raw Data'!B$2:B$81,$A8,'Raw Data'!R$2:R$81,">0")) -> 24.333333 | E8: =IF(SUMIFS('Raw Data'!K$2:K$81,'Raw Data'!B$2:B$81,$A8,'Raw Data'!S$2:S$81,"Stage 3")=0,"N/A",SUMIFS('Raw Data'!U$2:U$81,'Raw Data'!B$2:B$81,$A8,'Raw Data'!S$2:S$81,"Stage 3")/SUMIFS('Raw Data'!K$2:K$81,'Raw Data'!B$2:B$81,$A8,'Raw Data'!S$2:S$81,"Stage 3")) -> N/A | F8: 0.72 | G8: =SUMIFS('Raw Data'!U$2:U$81,'Raw Data'!B$2:B$81,$A8)/SUMIFS('Raw Data'!K$2:K$81,'Raw Data'!B$2:B$81,$A8) -> 0.036856794 | H8: =IF(C8<=0.05,"🟢 Green",IF(C8<=0.1,"🟡 Amber","🔴 Red")) -> 🔴 Red
A9: Mirabank | B9: {=1-SUMPRODUCT(('Raw Data'!B$2:B$81=$A9)*('Raw Data'!R$2:R$81>0)*('Raw Data'!K$2:K$81))/SUMIFS('Raw Data'!K$2:K$81,'Raw Data'!B$2:B$81,$A9)} -> 0.92836805 | C9: {=IF(SUMIFS('Raw Data'!K$2:K$81,'Raw Data'!B$2:B$81,$A9)=0,"-",SUMPRODUCT(('Raw Data'!B$2:B$81=$A9)*('Raw Data'!R$2:R$81>0)*('Raw Data'!K$2:K$81))/SUMIFS('Raw Data'!K$2:K$81,'Raw Data'!B$2:B$81,$A9))} -> 0.07163195 | D9: =IF(COUNTIFS('Raw Data'!B$2:B$81,$A9,'Raw Data'!R$2:R$81,">0")=0,"N/A",AVERAGEIFS('Raw Data'!R$2:R$81,'Raw Data'!B$2:B$81,$A9,'Raw Data'!R$2:R$81,">0")) -> 26 | E9: =IF(SUMIFS('Raw Data'!K$2:K$81,'Raw Data'!B$2:B$81,$A9,'Raw Data'!S$2:S$81,"Stage 3")=0,"N/A",SUMIFS('Raw Data'!U$2:U$81,'Raw Data'!B$2:B$81,$A9,'Raw Data'!S$2:S$81,"Stage 3")/SUMIFS('Raw Data'!K$2:K$81,'Raw Data'!B$2:B$81,$A9,'Raw Data'!S$2:S$81,"Stage 3")) -> N/A | F9: 0.85 | G9: =SUMIFS('Raw Data'!U$2:U$81,'Raw Data'!B$2:B$81,$A9)/SUMIFS('Raw Data'!K$2:K$81,'Raw Data'!B$2:B$81,$A9) -> 0.019121834 | H9: =IF(C9<=0.05,"🟢 Green",IF(C9<=0.1,"🟡 Amber","🔴 Red")) -> 🟡 Amber
A10: Lulo Bank | B10: {=IF(SUMIFS('Raw Data'!K$2:K$81,'Raw Data'!B$2:B$81,$A10)=0,"N/A",1-SUMPRODUCT(('Raw Data'!B$2:B$81=$A10)*('Raw Data'!R$2:R$81>0)*('Raw Data'!K$2:K$81))/SUMIFS('Raw Data'!K$2:K$81,'Raw Data'!B$2:B$81,$A10))} -> 1 | C10: {=IF(SUMIFS('Raw Data'!K$2:K$81,'Raw Data'!B$2:B$81,$A10)=0,"-",SUMPRODUCT(('Raw Data'!B$2:B$81=$A10)*('Raw Data'!R$2:R$81>0)*('Raw Data'!K$2:K$81))/SUMIFS('Raw Data'!K$2:K$81,'Raw Data'!B$2:B$81,$A10))} -> 0 | D10: =IF(COUNTIFS('Raw Data'!B$2:B$81,$A10,'Raw Data'!R$2:R$81,">0")=0,"N/A",AVERAGEIFS('Raw Data'!R$2:R$81,'Raw Data'!B$2:B$81,$A10,'Raw Data'!R$2:R$81,">0")) -> N/A | E10: N/A | F10: N/A | G10: =IF(SUMIFS('Raw Data'!K$2:K$81,'Raw Data'!B$2:B$81,$A10)=0,"N/A",SUMIFS('Raw Data'!U$2:U$81,'Raw Data'!B$2:B$81,$A10)/SUMIFS('Raw Data'!K$2:K$81,'Raw Data'!B$2:B$81,$A10)) -> 0.0067298868 | H10: =IF(C10="-","🟢 Green",IF(C10<=0.05,"🟢 Green",IF(C10<=0.1,"🟡 Amber","🔴 Red"))) -> 🟢 Green
A11: GROUP TOTAL | B11: {=1-SUMPRODUCT(('Raw Data'!R$2:R$81>0)*('Raw Data'!K$2:K$81))/SUM('Raw Data'!K$2:K$81)} -> 0.91802299 | C11: {=SUMPRODUCT(('Raw Data'!R$2:R$81>0)*('Raw Data'!K$2:K$81))/SUM('Raw Data'!K$2:K$81)} -> 0.081977009 | D11: =IF(COUNTIFS('Raw Data'!R$2:R$81,">0")=0,"N/A",AVERAGEIFS('Raw Data'!R$2:R$81,'Raw Data'!R$2:R$81,">0")) -> 33.571429 | G11: =SUM('Raw Data'!U$2:U$81)/SUM('Raw Data'!K$2:K$81) -> 0.022399424 | H11: =IF(C11<=0.05,"🟢 Green",IF(C11<=0.1,"🟡 Amber","🔴 Red")) -> 🟡 Amber
A13: 2. PAST DUE AGING BY ENTITY (USD mm)
A14: Entity | B14: Current (DPD=0) | C14: 1-30 DPD | D14: 31-60 DPD | E14: 61-90 DPD | F14: 90+ DPD | G14: Total Outstanding | H14: Overdue %
A15: Samman Capital | B15: {=SUMPRODUCT(('Raw Data'!B$2:B$81=$A15)*('Raw Data'!R$2:R$81=0)*('Raw Data'!K$2:K$81))} -> 556.02 | C15: {=SUMPRODUCT(('Raw Data'!B$2:B$81=$A15)*('Raw Data'!R$2:R$81>=1)*('Raw Data'!R$2:R$81<=30)*('Raw Data'!K$2:K$81))} -> 2.07 | D15: {=SUMPRODUCT(('Raw Data'!B$2:B$81=$A15)*('Raw Data'!R$2:R$81>=31)*('Raw Data'!R$2:R$81<=60)*('Raw Data'!K$2:K$81))} -> 0 | E15: {=SUMPRODUCT(('Raw Data'!B$2:B$81=$A15)*('Raw Data'!R$2:R$81>=61)*('Raw Data'!R$2:R$81<=90)*('Raw Data'!K$2:K$81))} -> 0 | F15: {=SUMPRODUCT(('Raw Data'!B$2:B$81=$A15)*('Raw Data'!R$2:R$81>90)*('Raw Data'!K$2:K$81))} -> 0 | G15: =SUM(B15:F15) -> 558.09 | H15: =IF(G15=0,"-",(G15-B15)/G15) -> 0.0037090792
A16: First Women Bank Ltd (FWBL)
A17: Beltone
A18: Mirabank
A19: Lulo Bank
A20: GROUP TOTAL

Sheet Watchlist
A1: WATCHLIST & PROBLEM ACCOUNT TRACKER
A2: Active watchlist accounts, problem exposures, and EWS-flagged facilities requiring action
A4: 1. WATCHLIST SUMMARY BY ENTITY
A5: Entity | B5: Watchlist Count | C5: Watchlist Exposure (USD mm) | D5: % of Entity Portfolio | E5: EWS Score ≥2 Count | F5: EWS Score ≥2 Exposure (USD mm) | G5: Stage 2+3 Count | H5: RAG
A6: Samman Capital | B6: =COUNTIFS('Raw Data'!B$2:B$81,$A6,'Raw Data'!Z$2:Z$81,"Yes") -> 1 | C6: =SUMIFS('Raw Data'!K$2:K$81,'Raw Data'!B$2:B$81,$A6,'Raw Data'!Z$2:Z$81,"Yes") -> 2.07 | D6: =IF(SUMIFS('Raw Data'!K$2:K$81,'Raw Data'!B$2:B$81,$A6)=0,"-",C6/SUMIFS('Raw Data'!K$2:K$81,'Raw Data'!B$2:B$81,$A6)) -> 0.0037090792 | E6: =COUNTIFS('Raw Data'!B$2:B$81,$A6,'Raw Data'!AA$2:AA$81,">="&2) -> 1 | F6: =SUMIFS('Raw Data'!K$2:K$81,'Raw Data'!B$2:B$81,$A6,'Raw Data'!AA$2:AA$81,">="&2) -> 2.07 | G6: =COUNTIFS('Raw Data'!B$2:B$81,$A6,'Raw Data'!S$2:S$81,"<>Stage 1") -> 1 | H6: =IF(D6="-","🟢 Green",IF(D6>0.1,"🔴 Red",IF(D6>0.05,"🟡 Amber","🟢 Green"))) -> 🟢 Green
A7: First Women Bank Ltd (FWBL) | B7: =COUNTIFS('Raw Data'!B$2:B$81,$A7,'Raw Data'!Z$2:Z$81,"Yes") -> 2 | C7: =SUMIFS('Raw Data'!K$2:K$81,'Raw Data'!B$2:B$81,$A7,'Raw Data'!Z$2:Z$81,"Yes") -> 10.1 | D7: =IF(SUMIFS('Raw Data'!K$2:K$81,'Raw Data'!B$2:B$81,$A7)=0,"-",C7/SUMIFS('Raw Data'!K$2:K$81,'Raw Data'!B$2:B$81,$A7)) -> 0.050935499 | E7: =COUNTIFS('Raw Data'!B$2:B$81,$A7,'Raw Data'!AA$2:AA$81,">="&2) -> 2 | F7: =SUMIFS('Raw Data'!K$2:K$81,'Raw Data'!B$2:B$81,$A7,'Raw Data'!AA$2:AA$81,">="&2) -> 10.1 | G7: =COUNTIFS('Raw Data'!B$2:B$81,$A7,'Raw Data'!S$2:S$81,"<>Stage 1") -> 2 | H7: =IF(D7="-","🟢 Green",IF(D7>0.1,"🔴 Red",IF(D7>0.05,"🟡 Amber","🟢 Green"))) -> 🟡 Amber
A8: Beltone | B8: =COUNTIFS('Raw Data'!B$2:B$81,$A8,'Raw Data'!Z$2:Z$81,"Yes") -> 5 | C8: =SUMIFS('Raw Data'!K$2:K$81,'Raw Data'!B$2:B$81,$A8,'Raw Data'!Z$2:Z$81,"Yes") -> 145.14 | D8: =IF(SUMIFS('Raw Data'!K$2:K$81,'Raw Data'!B$2:B$81,$A8)=0,"-",C8/SUMIFS('Raw Data'!K$2:K$81,'Raw Data'!B$2:B$81,$A8)) -> 0.33475563 | E8: =COUNTIFS('Raw Data'!B$2:B$81,$A8,'Raw Data'!AA$2:AA$81,">="&2) -> 5 | F8: =SUMIFS('Raw Data'!K$2:K$81,'Raw Data'!B$2:B$81,$A8,'Raw Data'!AA$2:AA$81,">="&2) -> 145.14 | G8: =COUNTIFS('Raw Data'!B$2:B$81,$A8,'Raw Data'!S$2:S$81,"<>Stage 1") -> 5 | H8: =IF(D8="-","🟢 Green",IF(D8>0.1,"🔴 Red",IF(D8>0.05,"🟡 Amber","🟢 Green"))) -> 🔴 Red
A9: Mirabank | B9: =COUNTIFS('Raw Data'!B$2:B$81,$A9,'Raw Data'!Z$2:Z$81,"Yes") -> 1 | C9: =SUMIFS('Raw Data'!K$2:K$81,'Raw Data'!B$2:B$81,$A9,'Raw Data'!Z$2:Z$81,"Yes") -> 23.9 | D9: =IF(SUMIFS('Raw Data'!K$2:K$81,'Raw Data'!B$2:B$81,$A9)=0,"-",C9/SUMIFS('Raw Data'!K$2:K$81,'Raw Data'!B$2:B$81,$A9)) -> 0.07163195 | E9: =COUNTIFS('Raw Data'!B$2:B$81,$A9,'Raw Data'!AA$2:AA$81,">="&2) -> 1 | F9: =SUMIFS('Raw Data'!K$2:K$81,'Raw Data'!B$2:B$81,$A9,'Raw Data'!AA$2:AA$81,">="&2) -> 23.9 | G9: =COUNTIFS('Raw Data'!B$2:B$81,$A9,'Raw Data'!S$2:S$81,"<>Stage 1") -> 1 | H9: =IF(D9="-","🟢 Green",IF(D9>0.1,"🔴 Red",IF(D9>0.05,"🟡 Amber","🟢 Green"))) -> 🟡 Amber
A10: Lulo Bank | B10: =COUNTIFS('Raw Data'!B$2:B$81,$A10,'Raw Data'!Z$2:Z$81,"Yes") -> 0 | C10: =SUMIFS('Raw Data'!K$2:K$81,'Raw Data'!B$2:B$81,$A10,'Raw Data'!Z$2:Z$81,"Yes") -> 0 | D10: =IF(SUMIFS('Raw Data'!K$2:K$81,'Raw Data'!B$2:B$81,$A10)=0,"-",C10/SUMIFS('Raw Data'!K$2:K$81,'Raw Data'!B$2:B$81,$A10)) -> 0 | E10: =COUNTIFS('Raw Data'!B$2:B$81,$A10,'Raw Data'!AA$2:AA$81,">="&2) -> 0 | F10: =SUMIFS('Raw Data'!K$2:K$81,'Raw Data'!B$2:B$81,$A10,'Raw Data'!AA$2:AA$81,">="&2) -> 0 | G10: =COUNTIFS('Raw Data'!B$2:B$81,$A10,'Raw Data'!S$2:S$81,"<>Stage 1") -> 0 | H10: =IF(D10="-","🟢 Green",IF(D10>0.1,"🔴 Red",IF(D10>0.05,"🟡 Amber","🟢 Green"))) -> 🟢 Green
A11: GROUP TOTAL | B11: =SUM(B6:B10) -> 9 | C11: =SUM(C6:C10) -> 181.21 | D11: =C11/SUM('Raw Data'!K2:K81) -> 0.11643717 | E11: =SUM(E6:E10) -> 9 | F11: =SUM(F6:F10) -> 181.21 | G11: =SUM(G6:G10) -> 9
A13: 2. DETAILED WATCHLIST REGISTER — All Facilities with Watchlist Flag = "Yes" or EWS Score ≥ 2
A14: Facility Ref | B14: Entity | C14: Obligor | D14: Product | E14: Outstanding (USD mm) | F14: DPD | G14: Stage | H14: Rating | I14: EWS Score | J14: EWS Triggers | K14: Action Required
A15: TF-1079 | B15: FWBL | C15: Bank Alfalah Corp | D15: Doc. Collection - D/P | E15: 3.59 | F15: 92 | G15: Stage 3 | H15: 10 | I15: 5 | J15: DPD>90, Sub-IG Rating, NPL | K15: 🔴 Immediate Write-down Review
A16: TF-1039 | B16: Beltone | C16: Oando PLC | D16: BG - Financial | E16: 26.5 | F16: 5 | G16: Stage 2 | H16: 8 | I16: 4 | J16: DPD>0, Sub-IG, Low Coll, Stage 2 | K16: 🟡 CRO Escalation
A17: TF-1064 | B17: Beltone | C17: Seplat Energy | D17: TL - Post-Import | E17: 36.42 | F17: 26 | G17: Stage 2 | H17: 9 | I17: 4 | J17: DPD>0, Sub-IG, Low Coll, Stage 2 | K17: 🟡 CRO Escalation
A18: TF-1067 | B18: Beltone | C18: Tullow Ghana | D18: BG - Financial | E18: 15.28 | F18: 0 | G18: Stage 2 | H18: 8 | I18: 4 | J18: Sub-IG, Low Coll, Stage 2, High Util | K18: 🟡 CRO Escalation
A19: TF-1076 | B19: Beltone | C19: East African Breweries | D19: TL - Pre-Export | E19: 28.59 | F19: 42 | G19: Stage 2 | H19: 9 | I19: 4 | J19: DPD>30, Sub-IG, Stage 2 | K19: 🟡 CRO Escalation
A20: TF-1024 | B20: Samman Capital | C20: Vedanta Resources | D20: Import LC | E20: 2.07 | F20: 19 | G20: Stage 2 | H20: 8 | I20: 3 | J20: DPD>0, Sub-IG, Stage 2 | K20: Enhanced Monitoring
A21: TF-1058 | B21: FWBL | C21: Nishat Mills | D21: TL - Post-Import | E21: 6.51 | F21: 25 | G21: Stage 2 | H21: 8 | I21: 3 | J21: DPD>0, Sub-IG, Stage 2 | K21: Enhanced Monitoring
A22: TF-1063 | B22: Mirabank | C22: Thyssenkrupp AG | D22: Import LC | E22: 23.9 | F22: 26 | G22: Stage 2 | H22: 7 | I22: 3 | J22: DPD>0, Stage 2, High Util | K22: Enhanced Monitoring
A23: TF-1080 | B23: Beltone | C23: Sibanye Stillwater | D23: Import LC | E23: 38.35 | F23: 0 | G23: Stage 2 | H23: 8 | I23: 3 | J23: Sub-IG, Low Coll, Stage 2 | K23: Enhanced Monitoring

Sheet EWS Dashboard
A1: EARLY WARNING SIGNAL (EWS) DASHBOARD
A2: Three-layer risk monitoring: Facility-level signals → Entity-level patterns → Macro/External triggers
A4: 1. EWS SCORE SUMMARY BY ENTITY
A5: Entity | B5: Score 0 (No Alert) | C5: Score 1 (Watch) | D5: Score 2 (Elevated) | E5: Score 3 (High) | F5: Score 4-5 (Critical) | G5: Total Facilities | H5: Avg EWS Score | I5: Flagged Exposure (USD mm) | J5: Entity EWS RAG
A6: Samman Capital | B6: =COUNTIFS('Raw Data'!B$2:B$81,$A6,'Raw Data'!AA$2:AA$81,0) -> 21 | C6: =COUNTIFS('Raw Data'!B$2:B$81,$A6,'Raw Data'!AA$2:AA$81,1) -> 7 | D6: =COUNTIFS('Raw Data'!B$2:B$81,$A6,'Raw Data'!AA$2:AA$81,2) -> 0 | E6: =COUNTIFS('Raw Data'!B$2:B$81,$A6,'Raw Data'!AA$2:AA$81,3) -> 1 | F6: =COUNTIFS('Raw Data'!B$2:B$81,$A6,'Raw Data'!AA$2:AA$81,">="&4) -> 0 | G6: =SUM(B6:F6) -> 29 | H6: =IF(G6=0,"-",AVERAGEIFS('Raw Data'!AA$2:AA$81,'Raw Data'!B$2:B$81,$A6)) -> 0.34482759 | I6: =SUMIFS('Raw Data'!K$2:K$81,'Raw Data'!B$2:B$81,$A6,'Raw Data'!AA$2:AA$81,">="&2) -> 2.07 | J6: =IF(H6>=2,"🔴 Critical",IF(H6>=1,"🟡 Elevated","🟢 Normal")) -> 🟢 Normal
A7: First Women Bank Ltd (FWBL) | B7: =COUNTIFS('Raw Data'!B$2:B$81,$A7,'Raw Data'!AA$2:AA$81,0) -> 8 | C7: =COUNTIFS('Raw Data'!B$2:B$81,$A7,'Raw Data'!AA$2:AA$81,1) -> 2 | D7: =COUNTIFS('Raw Data'!B$2:B$81,$A7,'Raw Data'!AA$2:AA$81,2) -> 0 | E7: =COUNTIFS('Raw Data'!B$2:B$81,$A7,'Raw Data'!AA$2:AA$81,3) -> 1 | F7: =COUNTIFS('Raw Data'!B$2:B$81,$A7,'Raw Data'!AA$2:AA$81,">="&4) -> 1 | G7: =SUM(B7:F7) -> 12 | H7: =IF(G7=0,"-",AVERAGEIFS('Raw Data'!AA$2:AA$81,'Raw Data'!B$2:B$81,$A7)) -> 0.83333333 | I7: =SUMIFS('Raw Data'!K$2:K$81,'Raw Data'!B$2:B$81,$A7,'Raw Data'!AA$2:AA$81,">="&2) -> 10.1 | J7: =IF(H7>=2,"🔴 Critical",IF(H7>=1,"🟡 Elevated","🟢 Normal")) -> 🟢 Normal
A8: Beltone | B8: =COUNTIFS('Raw Data'!B$2:B$81,$A8,'Raw Data'!AA$2:AA$81,0) -> 10 | C8: =COUNTIFS('Raw Data'!B$2:B$81,$A8,'Raw Data'!AA$2:AA$81,1) -> 4 | D8: =COUNTIFS('Raw Data'!B$2:B$81,$A8,'Raw Data'!AA$2:AA$81,2) -> 0 | E8: =COUNTIFS('Raw Data'!B$2:B$81,$A8,'Raw Data'!AA$2:AA$81,3) -> 1 | F8: =COUNTIFS('Raw Data'!B$2:B$81,$A8,'Raw Data'!AA$2:AA$81,">="&4) -> 4 | G8: =SUM(B8:F8) -> 19 | H8: =IF(G8=0,"-",AVERAGEIFS('Raw Data'!AA$2:AA$81,'Raw Data'!B$2:B$81,$A8)) -> 1.2105263 | I8: =SUMIFS('Raw Data'!K$2:K$81,'Raw Data'!B$2:B$81,$A8,'Raw Data'!AA$2:AA$81,">="&2) -> 145.14 | J8: =IF(H8>=2,"🔴 Critical",IF(H8>=1,"🟡 Elevated","🟢 Normal")) -> 🟡 Elevated
A9: Mirabank | B9: =COUNTIFS('Raw Data'!B$2:B$81,$A9,'Raw Data'!AA$2:AA$81,0) -> 15 | C9: =COUNTIFS('Raw Data'!B$2:B$81,$A9,'Raw Data'!AA$2:AA$81,1) -> 2 | D9: =COUNTIFS('Raw Data'!B$2:B$81,$A9,'Raw Data'!AA$2:AA$81,2) -> 0 | E9: =COUNTIFS('Raw Data'!B$2:B$81,$A9,'Raw Data'!AA$2:AA$81,3) -> 1 | F9: =COUNTIFS('Raw Data'!B$2:B$81,$A9,'Raw Data'!AA$2:AA$81,">="&4) -> 0 | G9: =SUM(B9:F9) -> 18 | H9: =IF(G9=0,"-",AVERAGEIFS('Raw Data'!AA$2:AA$81,'Raw Data'!B$2:B$81,$A9)) -> 0.27777778 | I9: =SUMIFS('Raw Data'!K$2:K$81,'Raw Data'!B$2:B$81,$A9,'Raw Data'!AA$2:AA$81,">="&2) -> 23.9 | J9: =IF(H9>=2,"🔴 Critical",IF(H9>=1,"🟡 Elevated","🟢 Normal")) -> 🟢 Normal
A10: Lulo Bank | B10: =COUNTIFS('Raw Data'!B$2:B$81,$A10,'Raw Data'!AA$2:AA$81,0) -> 2 | C10: =COUNTIFS('Raw Data'!B$2:B$81,$A10,'Raw Data'!AA$2:AA$81,1) -> 0 | D10: =COUNTIFS('Raw Data'!B$2:B$81,$A10,'Raw Data'!AA$2:AA$81,2) -> 0 | E10: =COUNTIFS('Raw Data'!B$2:B$81,$A10,'Raw Data'!AA$2:AA$81,3) -> 0 | F10: =COUNTIFS('Raw Data'!B$2:B$81,$A10,'Raw Data'!AA$2:AA$81,">="&4) -> 0 | G10: =SUM(B10:F10) -> 2 | H10: =IF(G10=0,"-",AVERAGEIFS('Raw Data'!AA$2:AA$81,'Raw Data'!B$2:B$81,$A10)) -> 0 | I10: =SUMIFS('Raw Data'!K$2:K$81,'Raw Data'!B$2:B$81,$A10,'Raw Data'!AA$2:AA$81,">="&2) -> 0 | J10: =IF(H10>=2,"🔴 Critical",IF(H10>=1,"🟡 Elevated","🟢 Normal")) -> 🟢 Normal
A11: GROUP TOTAL | B11: =SUM(B6:B10) -> 56 | C11: =SUM(C6:C10) -> 15 | D11: =SUM(D6:D10) -> 0 | E11: =SUM(E6:E10) -> 4 | F11: =SUM(F6:F10) -> 5 | G11: =SUM(G6:G10) -> 80 | H11: =AVERAGE('Raw Data'!AA2:AA81) -> 0.6 | I11: =SUM(I6:I10) -> 181.21
A13: 2. STAGE MIGRATION MATRIX (Current Month vs. Implied Prior Stage)
C14: Current Month Stage → | H14: Key Migration Metrics | I14: Value | J14: RAG
A15: Prior Stage ↓ | C15: Stage 1 | D15: Stage 2 | E15: Stage 3 | F15: Total Prior | H15: Downgrade Rate (S1→S2) | I15: =IF(F16=0,"-",D16/F16) -> 0.08 | J15: =IF(I15<=0.05,"🟢 Green",IF(I15<=0.1,"🟡 Amber","🔴 Red")) -> 🟡 Amber
A16: Stage 1 (Performing) | B16: # Facilities | C16: 69 | D16: 6 | E16: 0 | F16: =SUM(C16:E16) -> 75 | H16: Default Rate (S1→S3) | I16: =IF(F16=0,"-",E16/F16) -> 0 | J16: =IF(I16<=0.02,"🟢 Green",IF(I16<=0.05,"🟡 Amber","🔴 Red")) -> 🟢 Green
A17: Stage 2 (Underperforming) | B17: # Facilities | C17: 2 | D17: 2 | E17: 1 | F17: =SUM(C17:E17) -> 5 | H17: Cure Rate (S2→S1) | I17: =IF(F17=0,"-",C17/F17) -> 0.4 | J17: =IF(I17>=0.3,"🟢 Green",IF(I17>=0.15,"🟡 Amber","🔴 Red")) -> 🟢 Green
A18: Stage 3 (NPL) | B18: # Facilities | C18: 0 | D18: 0 | E18: 0 | F18: =SUM(C18:E18) -> 0 | H18: Roll Rate (S2→S3) | I18: =IF(F17=0,"-",E17/F17) -> 0.2 | J18: =IF(I18<=0.1,"🟢 Green",IF(I18<=0.2,"🟡 Amber","🔴 Red")) -> 🟡 Amber
A19: Total Current | C19: =SUM(C16:C18) -> 71 | D19: =SUM(D16:D18) -> 8 | E19: =SUM(E16:E18) -> 1 | F19: =SUM(F16:F18) -> 80 | H19: Net Stage Migration | I19: =D16+E16-C17 -> 4 | J19: =IF(I19<=2,"🟢 Green",IF(I19<=5,"🟡 Amber","🔴 Red")) -> 🟡 Amber
A21: 3. DPD ROLL RATE ANALYSIS — Probability of Moving to Worse DPD Bucket
A22: DPD Transition | B22: # Facilities (Prior) | C22: # Rolled Forward | D22: # Stayed / Cured | E22: Roll Rate | F22: Exposure at Risk (USD mm) | G22: RAG
A23: Current → 1-30 DPD | B23: 75 | C23: 5 | D23: =B23-C23 -> 70 | E23: =C23/B23 -> 0.066666667 | F23: 95.4 | G23: =IF(E23<=0.05,"🟢 Green",IF(E23<=0.1,"🟡 Amber","🔴 Red")) -> 🟡 Amber
A24: 1-30 DPD → 31-60 DPD | B24: 8 | C24: 2 | D24: =B24-C24 -> 6 | E24: =C24/B24 -> 0.25 | F24: 28.59 | G24: =IF(E24<=0.15,"🟢 Green",IF(E24<=0.3,"🟡 Amber","🔴 Red")) -> 🟡 Amber
A25: 31-60 DPD → 61-90 DPD | B25: 3 | C25: 0 | D25: =B25-C25 -> 3 | E25: =IF(B25=0,"-",C25/B25) -> 0 | F25: 0 | G25: =IF(E25="-","🟢 Green",IF(E25<=0.2,"🟢 Green",IF(E25<=0.4,"🟡 Amber","🔴 Red"))) -> 🟢 Green
A26: 61-90 DPD → 90+ DPD (NPL) | B26: 1 | C26: 1 | D26: =B26-C26 -> 0 | E26: =IF(B26=0,"-",C26/B26) -> 1 | F26: 3.59 | G26: =IF(E26="-","🟢 Green",IF(E26<=0.3,"🟢 Green",IF(E26<=0.5,"🟡 Amber","🔴 Red"))) -> 🔴 Red
A28: Implied NPL Pipeline (next 3 months) | E28: =E23*E24*E26 -> 0.016666667 | F28: =SUM('Raw Data'!K2:K81)*E28 -> 25.938167

Sheet Macro & External Risk
A1: MACRO & EXTERNAL RISK MONITOR
A2: FX risk, sovereign/country risk, and regulatory risk monitoring per entity jurisdiction
A4: 1. FX RISK MONITOR BY ENTITY CORRIDOR
A5: Entity | B5: Primary Currency | C5: FX Rate (vs USD) | D5: 30-Day Volatility | E5: 90-Day Volatility | F5: YTD Depreciation | G5: Portfolio Exposure (USD mm) | H5: FX-Adjusted Impact (USD mm) | I5: Capital Controls? | J5: Transfer Risk | K5: FX RAG
A6: Samman Capital | B6: INR | C6: 83.5 | D6: 0.028 | E6: 0.045 | F6: -0.018 | G6: =SUMIFS('Raw Data'!K$2:K$81,'Raw Data'!B$2:B$81,$A6) -> 558.09 | H6: =G6*ABS(F6) -> 10.04562 | I6: No | J6: Low | K6: =IF(ABS(F6)>0.1,"🔴 High",IF(ABS(F6)>0.05,"🟡 Medium","🟢 Low")) -> 🟢 Low
A7: First Women Bank Ltd (FWBL) | B7: PKR | C7: 278.5 | D7: 0.065 | E7: 0.11 | F7: -0.085 | G7: =SUMIFS('Raw Data'!K$2:K$81,'Raw Data'!B$2:B$81,$A7) -> 198.29 | H7: =G7*ABS(F7) -> 16.85465 | I7: Partial | J7: High | K7: =IF(ABS(F7)>0.1,"🔴 High",IF(ABS(F7)>0.05,"🟡 Medium","🟢 Low")) -> 🟡 Medium
A8: Beltone | B8: EGP | C8: 50.8 | D8: 0.082 | E8: 0.145 | F8: -0.12 | G8: =SUMIFS('Raw Data'!K$2:K$81,'Raw Data'!B$2:B$81,$A8) -> 433.57 | H8: =G8*ABS(F8) -> 52.0284 | I8: Yes | J8: Very High | K8: =IF(ABS(F8)>0.1,"🔴 High",IF(ABS(F8)>0.05,"🟡 Medium","🟢 Low")) -> 🔴 High
A9: Mirabank | B9: RSD / EUR | C9: 117.2 | D9: 0.015 | E9: 0.025 | F9: -0.022 | G9: =SUMIFS('Raw Data'!K$2:K$81,'Raw Data'!B$2:B$81,$A9) -> 333.65 | H9: =G9*ABS(F9) -> 7.3403 | I9: No | J9: Low | K9: =IF(ABS(F9)>0.1,"🔴 High",IF(ABS(F9)>0.05,"🟡 Medium","🟢 Low")) -> 🟢 Low
A10: Lulo Bank | B10: COP | C10: 4150 | D10: 0.042 | E10: 0.068 | F10: -0.035 | G10: =SUMIFS('Raw Data'!K$2:K$81,'Raw Data'!B$2:B$81,$A10) -> 32.69 | H10: =G10*ABS(F10) -> 1.14415 | I10: No | J10: Medium | K10: =IF(ABS(F10)>0.1,"🔴 High",IF(ABS(F10)>0.05,"🟡 Medium","🟢 Low")) -> 🟢 Low
A11: GROUP FX IMPACT | G11: =SUM(G6:G10) -> 1556.29 | H11: =SUM(H6:H10) -> 87.41312
A13: 2. COUNTRY / SOVEREIGN RISK SCORECARD
A14: Entity / Jurisdiction | B14: Sovereign Rating (S&P) | C14: Sovereign Outlook | D14: CDS Spread (bps) | E14: Political Stability Score | F14: Sanctions Exposure | G14: Recent Events / Flags | J14: Country Risk Score (1-10) | K14: RAG
A15: Samman Capital — India | B15: BBB- | C15: Stable | D15: 95 | E15: 46183 | F15: None | G15: RBI tightening cycle; stable macro outlook | J15: 3 | K15: =IF(J15>=7,"🔴 High",IF(J15>=4,"🟡 Medium","🟢 Low")) -> 🟢 Low
A16: FWBL — Pakistan | B16: CCC+ | C16: Stable | D16: 680 | E16: 46091 | F16: None | G16: IMF programme ongoing; capital controls; high inflation | J16: 7 | K16: =IF(J16>=7,"🔴 High",IF(J16>=4,"🟡 Medium","🟢 Low")) -> 🔴 High
A17: Beltone — Egypt | B17: B- | C17: Positive | D17: 550 | E17: 46122 | F17: None | G17: FX liberalization ongoing; IMF deal; capital controls easing | J17: 7 | K17: =IF(J17>=7,"🔴 High",IF(J17>=4,"🟡 Medium","🟢 Low")) -> 🔴 High
A18: Mirabank — Serbia / Baltics | B18: BB+ | C18: Positive | D18: 180 | E18: 46152 | F18: Indirect (Russia-adj.) | G18: EU accession path; secondary sanctions risk from Russia trade corridor | J18: 5 | K18: =IF(J18>=7,"🔴 High",IF(J18>=4,"🟡 Medium","🟢 Low")) -> 🟡 Medium
A19: Lulo Bank — Colombia | B19: BB+ | C19: Stable | D19: 220 | E19: 46152 | F19: None | G19: Fiscal consolidation; moderate political risk; pension reform | J19: 4 | K19: =IF(J19>=7,"🔴 High",IF(J19>=4,"🟡 Medium","🟢 Low")) -> 🟡 Medium
A20: Africa Corridor (via Beltone) | B20: B to BB- | C20: Mixed | D20: 450 | E20: 46091 | F20: Selective | G20: Nigeria FX controls; Kenya debt distress; Ghana restructuring | J20: 8 | K20: =IF(J20>=7,"🔴 High",IF(J20>=4,"🟡 Medium","🟢 Low")) -> 🔴 High
A21: GROUP WEIGHTED AVG | J21: =SUMPRODUCT(J15:J19,G6:G10)/SUM(G6:G10) -> 5.0737973 | K21: =IF(J21>=7,"🔴 High",IF(J21>=4,"🟡 Medium","🟢 Low")) -> 🟡 Medium
A23: 3. REGULATORY RISK TRACKER BY JURISDICTION
A24: Entity / Jurisdiction | B24: Central Bank Regulator | C24: Policy Rate | D24: Rate Direction | E24: Basel Framework | F24: LCR/NSFR Compliance | G24: TF-Specific Regulations | H24: AML/CFT Regime | I24: Recent Regulatory Events | K24: Regulatory Risk RAG
A25: Samman Capital — India | B25: RBI | C25: 0.065 | D25: Hold | E25: Basel III+ | F25: Compliant | G25: FEMA; RBI TF Guidelines; LC margin rules | H25: Strong | I25: RBI tightened LC issuance norms; digital TF push | K25: 🟢 Low
A26: FWBL — Pakistan | B26: SBP | C26: 0.175 | D26: Cutting | E26: Basel III | F26: Under stress | G26: SBP LC limit caps; FX controls on imports | H26: FATF Grey List exit | I26: Import restrictions eased; SBP circular on TF limits | K26: 🔴 High
A27: Beltone — Egypt | B27: CBE | C27: 0.2775 | D27: Hold | E27: Basel II+ | F27: Constrained | G27: CBE FX allocation rules; LC opening restrictions | H27: Moderate | I27: FX unification; CBE eased LC restrictions partially | K27: 🔴 High
A28: Mirabank — Serbia / Baltics | B28: NBS / ECB | C28: 0.0575 | D28: Cutting | E28: Basel III (EU aligned) | F28: Compliant | G28: EU harmonized; EBRD trade facilitation programme | H28: EU standard | I28: Serbia aligning with EU acquis; sanctions compliance | K28: 🟢 Low
A29: Lulo Bank — Colombia | B29: BanRep | C29: 0.0975 | D29: Cutting | E29: Basel III | F29: Compliant | G29: SFC trade finance norms; FX hedging requirements | H29: FATF Compliant | I29: Rate cutting cycle; pension reform uncertainty | K29: 🟡 Medium
A30: HQ Group — UAE (Consolidation) | B30: CBUAE | C30: 0.0515 | D30: Fed-linked | E30: Basel III+ | F30: Compliant | G30: CBUAE group-level TF reporting; AML/sanctions framework | H30: Strong | I30: CBUAE enhanced group supervision; ESG disclosure | K30: 🟢 Low
A32: 4. COMPOSITE RISK HEAT MAP — ALL LAYERS COMBINED
A33: Entity | B33: Portfolio EWS Score (Avg) | C33: FX Risk Score | D33: Country Risk Score | E33: Regulatory Risk Score | F33: Composite Score (1-10) | G33: Exposure (USD mm) | H33: % of Group | I33: Risk-Weighted Exposure | J33: Action Required | K33: Overall RAG
A34: Samman Capital | B34: ='EWS Dashboard'!H6 -> 0.34482759 | C34: =ABS(F6)*100 -> 1.8 | D34: =J15 -> 3 | E34: 2 | F34: =MIN(10,(B34*2+C34+D34*2+E34)/6*10/5) -> 3.4965517 | G34: =G6 -> 558.09 | H34: =G34/SUM(G$34:G$38) -> 0.35860283 | I34: =G34*F34/10 -> 195.13906 | J34: =IF(F34>=7,"CRO Escalation Required",IF(F34>=4,"Enhanced Monitoring","Routine Review")) -> Routine Review | K34: =IF(F34>=7,"🔴 Critical",IF(F34>=4,"🟡 Elevated","🟢 Normal")) -> 🟢 Normal
A35: First Women Bank Ltd (FWBL) | B35: ='EWS Dashboard'!H7 -> 0.83333333 | C35: =ABS(F7)*100 -> 8.5 | D35: =J16 -> 7 | E35: 8 | F35: =MIN(10,(B35*2+C35+D35*2+E35)/6*10/5) -> 10 | G35: =G7 -> 198.29 | H35: =G35/SUM(G$34:G$38) -> 0.12741199 | I35: =G35*F35/10 -> 198.29 | J35: =IF(F35>=7,"CRO Escalation Required",IF(F35>=4,"Enhanced Monitoring","Routine Review")) -> CRO Escalation Required | K35: =IF(F35>=7,"🔴 Critical",IF(F35>=4,"🟡 Elevated","🟢 Normal")) -> 🔴 Critical
A36: Beltone | B36: ='EWS Dashboard'!H8 -> 1.2105263 | C36: =ABS(F8)*100 -> 12 | D36: =J17 -> 7 | E36: 8 | F36: =MIN(10,(B36*2+C36+D36*2+E36)/6*10/5) -> 10 | G36: =G8 -> 433.57 | H36: =G36/SUM(G$34:G$38) -> 0.27859204 | I36: =G36*F36/10 -> 433.57 | J36: =IF(F36>=7,"CRO Escalation Required",IF(F36>=4,"Enhanced Monitoring","Routine Review")) -> CRO Escalation Required | K36: =IF(F36>=7,"🔴 Critical",IF(F36>=4,"🟡 Elevated","🟢 Normal")) -> 🔴 Critical
A37: Mirabank | B37: ='EWS Dashboard'!H9 -> 0.27777778 | C37: =ABS(F9)*100 -> 2.2 | D37: =J18 -> 5 | E37: 3 | F37: =MIN(10,(B37*2+C37+D37*2+E37)/6*10/5) -> 5.2518519 | G37: =G9 -> 333.65 | H37: =G37/SUM(G$34:G$38) -> 0.21438806 | I37: =G37*F37/10 -> 175.22804 | J37: =IF(F37>=7,"CRO Escalation Required",IF(F37>=4,"Enhanced Monitoring","Routine Review")) -> Enhanced Monitoring | K37: =IF(F37>=7,"🔴 Critical",IF(F37>=4,"🟡 Elevated","🟢 Normal")) -> 🟡 Elevated
A38: Lulo Bank | B38: ='EWS Dashboard'!H10 -> 0 | C38: =ABS(F10)*100 -> 3.5 | D38: =J19 -> 4 | E38: 4 | F38: =MIN(10,(B38*2+C38+D38*2+E38)/6*10/5) -> 5.1666667 | G38: =G10 -> 32.69 | H38: =G38/SUM(G$34:G$38) -> 0.021005083 | I38: =G38*F38/10 -> 16.889833 | J38: =IF(F38>=7,"CRO Escalation Required",IF(F38>=4,"Enhanced Monitoring","Routine Review")) -> Enhanced Monitoring | K38: =IF(F38>=7,"🔴 Critical",IF(F38>=4,"🟡 Elevated","🟢 Normal")) -> 🟡 Elevated
A39: GROUP COMPOSITE | B39: =AVERAGE(B34:B38) -> 0.533293 | C39: =AVERAGE(C34:C38) -> 5.6 | D39: =SUMPRODUCT(D34:D38,G34:G38)/SUM(G34:G38) -> 5.0737973 | E39: =SUMPRODUCT(E34:E38,G34:G38)/SUM(G34:G38) -> 4.6924224 | F39: =SUMPRODUCT(F34:F38,G34:G38)/SUM(G34:G38) -> 6.5483742 | G39: =SUM(G34:G38) -> 1556.29 | H39: 1 | I39: =SUM(I34:I38) -> 1019.1169 | J39: =IF(F39>=7,"CRO Escalation Required",IF(F39>=4,"Enhanced Monitoring","Routine Review")) -> Enhanced Monitoring | K39: =IF(F39>=7,"🔴 Critical",IF(F39>=4,"🟡 Elevated","🟢 Normal")) -> 🟡 Elevated

Sheet Raw Data
A1: Facility Reference | B1: Entity | C1: Obligor Name | D1: Region | E1: Country | F1: Sector | G1: Commodity | H1: Product Type | I1: Currency | J1: Facility Limit (USD mm) | K1: Outstanding (USD mm) | L1: Prev Month Outstanding (USD mm) | M1: Tenor (Days) | N1: Start Date | O1: Maturity Date | P1: Internal Rating (1-10) | Q1: External Rating | R1: Days Past Due | S1: IFRS 9 Stage | T1: Provision Rate | U1: Provision Amount (USD mm) | V1: Collateral Value (USD mm) | W1: Collateral Coverage (%) | X1: Risk Weight | Y1: Counterparty Bank | Z1: Watchlist Flag | AA1: EWS Score (1-5) | AB1: EWS Triggers
A2: TF-1001 | B2: Samman Capital | C2: JBS Trading | D2: LATAM | E2: Brazil | F2: Agriculture & Food | G2: Rice | H2: Trade Loan - Post-Import | I2: USD | J2: 28.04 | K2: 26.83 | L2: 24.41 | M2: 52 | N2: 45579 | O2: 45631 | P2: 6 | Q2: BBB | R2: 0 | S2: Stage 1 | T2: 0.0083 | U2: 0.22 | V2: 22.27 | W2: 0.83 | X2: 0.75 | Y2: N/A | Z2: No | AA2: =MIN(5,(IF(R2>90,3,IF(R2>30,2,IF(R2>0,1,0))))+IF(P2*1>=8,1,0)+IF(W2<0.7,1,0)+IF(S2="Stage 3",2,IF(S2="Stage 2",1,0))+IF(K2/J2>0.95,1,0)) -> 1 | AB2: =IF(AA2=0,"None",_xlfn.TEXTJOIN(", ",TRUE,IF(R2>90,"DPD>90",IF(R2>30,"DPD>30",IF(R2>0,"DPD>0",""))),IF(P2*1>=8,"Sub-IG Rating",""),IF(W2<0.7,"Low Collateral",""),IF(S2="Stage 3","NPL",IF(S2="Stage 2","Stage 2","")),IF(K2/J2>0.95,"High Utilization",""))) -> High Utilization
A3: TF-1002 | B3: Samman Capital | C3: Reliance Industries | D3: India | E3: India | F3: Agriculture & Food | G3: Sugar | H3: Import LC | I3: USD | J3: 31.19 | K3: 24.67 | L3: 27.91 | M3: 124 | N3: 45481 | O3: 45605 | P3: 4 | Q3: A | R3: 0 | S3: Stage 1 | T3: 0.0102 | U3: 0.25 | V3: 22.93 | W3: 0.93 | X3: 0.5 | Y3: Standard Chartered | Z3: No | AA3: =MIN(5,(IF(R3>90,3,IF(R3>30,2,IF(R3>0,1,0))))+IF(P3*1>=8,1,0)+IF(W3<0.7,1,0)+IF(S3="Stage 3",2,IF(S3="Stage 2",1,0))+IF(K3/J3>0.95,1,0)) -> 0 | AB3: =IF(AA3=0,"None",_xlfn.TEXTJOIN(", ",TRUE,IF(R3>90,"DPD>90",IF(R3>30,"DPD>30",IF(R3>0,"DPD>0",""))),IF(P3*1>=8,"Sub-IG Rating",""),IF(W3<0.7,"Low Collateral",""),IF(S3="Stage 3","NPL",IF(S3="Stage 2","Stage 2","")),IF(K3/J3>0.95,"High Utilization",""))) -> None
A4: TF-1003 | B4: First Women Bank Ltd (FWBL) | C4: Engro Corporation | D4: Pakistan | E4: Pakistan | F4: Petrochemicals | G4: PVC | H4: Import LC | I4: USD | J4: 31.57 | K4: 30.67 | L4: 31.24 | M4: 157 | N4: 45362 | O4: 45519 | P4: 5 | Q4: BBB+ | R4: 0 | S4: Stage 1 | T4: 0.0086 | U4: 0.26 | V4: 25.45 | W4: 0.83 | X4: 0.5 | Y4: Barclays | Z4: No | AA4: =MIN(5,(IF(R4>90,3,IF(R4>30,2,IF(R4>0,1,0))))+IF(P4*1>=8,1,0)+IF(W4<0.7,1,0)+IF(S4="Stage 3",2,IF(S4="Stage 2",1,0))+IF(K4/J4>0.95,1,0)) -> 1 | AB4: =IF(AA4=0,"None",_xlfn.TEXTJOIN(", ",TRUE,IF(R4>90,"DPD>90",IF(R4>30,"DPD>30",IF(R4>0,"DPD>0",""))),IF(P4*1>=8,"Sub-IG Rating",""),IF(W4<0.7,"Low Collateral",""),IF(S4="Stage 3","NPL",IF(S4="Stage 2","Stage 2","")),IF(K4/J4>0.95,"High Utilization",""))) -> High Utilization
A5: TF-1004 | B5: Mirabank | C5: Vitol BV | D5: Europe | E5: Netherlands | F5: Metals & Mining | G5: Aluminum | H5: Export LC | I5: USD | J5: 35.72 | K5: 22.64 | L5: 21.84 | M5: 87 | N5: 45323 | O5: 45410 | P5: 3 | Q5: A+ | R5: 0 | S5: Stage 1 | T5: 0.0058 | U5: 0.13 | V5: 24.22 | W5: 1.07 | X5: 0.2 | Y5: Access Bank | Z5: No | AA5: =MIN(5,(IF(R5>90,3,IF(R5>30,2,IF(R5>0,1,0))))+IF(P5*1>=8,1,0)+IF(W5<0.7,1,0)+IF(S5="Stage 3",2,IF(S5="Stage 2",1,0))+IF(K5/J5>0.95,1,0)) -> 0 | AB5: =IF(AA5=0,"None",_xlfn.TEXTJOIN(", ",TRUE,IF(R5>90,"DPD>90",IF(R5>30,"DPD>30",IF(R5>0,"DPD>0",""))),IF(P5*1>=8,"Sub-IG Rating",""),IF(W5<0.7,"Low Collateral",""),IF(S5="Stage 3","NPL",IF(S5="Stage 2","Stage 2","")),IF(K5/J5>0.95,"High Utilization",""))) -> None
A6: TF-1005 | B6: Samman Capital | C6: Gulf Petrochem | D6: UAE | E6: UAE | F6: Manufacturing | G6: Machinery | H6: Trade Loan - Pre-Export | I6: USD | J6: 29.57 | K6: 26.93 | L6: 29.7 | M6: 138 | N6: 45480 | O6: 45618 | P6: 5 | Q6: BBB+ | R6: 0 | S6: Stage 1 | T6: 0.0098 | U6: 0.26 | V6: 25.75 | W6: 0.96 | X6: 0.5 | Y6: N/A | Z6: No | AA6: =MIN(5,(IF(R6>90,3,IF(R6>30,2,IF(R6>0,1,0))))+IF(P6*1>=8,1,0)+IF(W6<0.7,1,0)+IF(S6="Stage 3",2,IF(S6="Stage 2",1,0))+IF(K6/J6>0.95,1,0)) -> 0 | AB6: =IF(AA6=0,"None",_xlfn.TEXTJOIN(", ",TRUE,IF(R6>90,"DPD>90",IF(R6>30,"DPD>30",IF(R6>0,"DPD>0",""))),IF(P6*1>=8,"Sub-IG Rating",""),IF(W6<0.7,"Low Collateral",""),IF(S6="Stage 3","NPL",IF(S6="Stage 2","Stage 2","")),IF(K6/J6>0.95,"High Utilization",""))) -> None
A7: TF-1006 | B7: First Women Bank Ltd (FWBL) | C7: Tabreed | D7: UAE | E7: UAE | F7: Consumer Goods | G7: FMCG | H7: Import LC | I7: USD | J7: 36.06 | K7: 30.09 | L7: 33.86 | M7: 30 | N7: 45555 | O7: 45585 | P7: 3 | Q7: A+ | R7: 0 | S7: Stage 1 | T7: 0.0199 | U7: 0.6 | V7: 32.5 | W7: 1.08 | X7: 0.2 | Y7: Commerzbank | Z7: No | AA7: =MIN(5,(IF(R7>90,3,IF(R7>30,2,IF(R7>0,1,0))))+IF(P7*1>=8,1,0)+IF(W7<0.7,1,0)+IF(S7="Stage 3",2,IF(S7="Stage 2",1,0))+IF(K7/J7>0.95,1,0)) -> 0 | AB7: =IF(AA7=0,"None",_xlfn.TEXTJOIN(", ",TRUE,IF(R7>90,"DPD>90",IF(R7>30,"DPD>30",IF(R7>0,"DPD>0",""))),IF(P7*1>=8,"Sub-IG Rating",""),IF(W7<0.7,"Low Collateral",""),IF(S7="Stage 3","NPL",IF(S7="Stage 2","Stage 2","")),IF(K7/J7>0.95,"High Utilization",""))) -> None
A8: TF-1007 | B8: Beltone | C8: Gulf Petrochem | D8: UAE | E8: UAE | F8: Electronics & Technology | G8: Consumer Electronics | H8: Supply Chain Finance | I8: USD | J8: 11.96 | K8: 11.4 | L8: 12.11 | M8: 53 | N8: 45575 | O8: 45628 | P8: 6 | Q8: BBB | R8: 0 | S8: Stage 1 | T8: 0.0091 | U8: 0.1 | V8: 10.72 | W8: 0.94 | X8: 0.75 | Y8: N/A | Z8: No | AA8: =MIN(5,(IF(R8>90,3,IF(R8>30,2,IF(R8>0,1,0))))+IF(P8*1>=8,1,0)+IF(W8<0.7,1,0)+IF(S8="Stage 3",2,IF(S8="Stage 2",1,0))+IF(K8/J8>0.95,1,0)) -> 1 | AB8: =IF(AA8=0,"None",_xlfn.TEXTJOIN(", ",TRUE,IF(R8>90,"DPD>90",IF(R8>30,"DPD>30",IF(R8>0,"DPD>0",""))),IF(P8*1>=8,"Sub-IG Rating",""),IF(W8<0.7,"Low Collateral",""),IF(S8="Stage 3","NPL",IF(S8="Stage 2","Stage 2","")),IF(K8/J8>0.95,"High Utilization",""))) -> High Utilization
A9: TF-1008 | B9: Beltone | C9: Sappi Limited | D9: Africa | E9: South Africa | F9: Agriculture & Food | G9: Palm Oil | H9: Import LC | I9: USD | J9: 33.87 | K9: 25.06 | L9: 23.57 | M9: 136 | N9: 45610 | O9: 45746 | P9: 3 | Q9: A+ | R9: 0 | S9: Stage 1 | T9: 0.0155 | U9: 0.39 | V9: 22.55 | W9: 0.9 | X9: 0.2 | Y9: Citi | Z9: No | AA9: =MIN(5,(IF(R9>90,3,IF(R9>30,2,IF(R9>0,1,0))))+IF(P9*1>=8,1,0)+IF(W9<0.7,1,0)+IF(S9="Stage 3",2,IF(S9="Stage 2",1,0))+IF(K9/J9>0.95,1,0)) -> 0 | AB9: =IF(AA9=0,"None",_xlfn.TEXTJOIN(", ",TRUE,IF(R9>90,"DPD>90",IF(R9>30,"DPD>30",IF(R9>0,"DPD>0",""))),IF(P9*1>=8,"Sub-IG Rating",""),IF(W9<0.7,"Low Collateral",""),IF(S9="Stage 3","NPL",IF(S9="Stage 2","Stage 2","")),IF(K9/J9>0.95,"High Utilization",""))) -> None
A10: TF-1009 | B10: Beltone | C10: Orascom Construction | D10: Africa | E10: Egypt | F10: Oil & Gas | G10: LNG | H10: Bank Guarantee - Performance | I10: USD | J10: 22.91 | K10: 22.45 | L10: 20.49 | M10: 139 | N10: 45340 | O10: 45480 | P10: 4 | Q10: A | R10: 0 | S10: Stage 1 | T10: 0.0144 | U10: 0.32 | V10: 17.96 | W10: 0.8 | X10: 0.5 | Y10: ING Bank | Z10: No | AA10: =MIN(5,(IF(R10>90,3,IF(R10>30,2,IF(R10>0,1,0))))+IF(P10*1>=8,1,0)+IF(W10<0.7,1,0)+IF(S10="Stage 3",2,IF(S10="Stage 2",1,0))+IF(K10/J10>0.95,1,0)) -> 1 | AB10: =IF(AA10=0,"None",_xlfn.TEXTJOIN(", ",TRUE,IF(R10>90,"DPD>90",IF(R10>30,"DPD>30",IF(R10>0,"DPD>0",""))),IF(P10*1>=8,"Sub-IG Rating",""),IF(W10<0.7,"Low Collateral",""),IF(S10="Stage 3","NPL",IF(S10="Stage 2","Stage 2","")),IF(K10/J10>0.95,"High Utilization",""))) -> High Utilization
A11: TF-1010 | B11: Mirabank | C11: Al Ghurair Resources | D11: UAE | E11: UAE | F11: Shipping & Logistics | G11: Freight | H11: Trade Loan - Pre-Export | I11: USD | J11: 13.56 | K11: 11.51 | L11: 13.21 | M11: 72 | N11: 45612 | O11: 45684 | P11: 7 | Q11: BB+ | R11: 0 | S11: Stage 1 | T11: 0.0066 | U11: 0.08 | V11: 7.48 | W11: 0.65 | X11: 0.75 | Y11: N/A | Z11: No | AA11: =MIN(5,(IF(R11>90,3,IF(R11>30,2,IF(R11>0,1,0))))+IF(P11*1>=8,1,0)+IF(W11<0.7,1,0)+IF(S11="Stage 3",2,IF(S11="Stage 2",1,0))+IF(K11/J11>0.95,1,0)) -> 1 | AB11: =IF(AA11=0,"None",_xlfn.TEXTJOIN(", ",TRUE,IF(R11>90,"DPD>90",IF(R11>30,"DPD>30",IF(R11>0,"DPD>0",""))),IF(P11*1>=8,"Sub-IG Rating",""),IF(W11<0.7,"Low Collateral",""),IF(S11="Stage 3","NPL",IF(S11="Stage 2","Stage 2","")),IF(K11/J11>0.95,"High Utilization",""))) -> Low Collateral
A12: TF-1011 | B12: Samman Capital | C12: Reliance Industries | D12: India | E12: India | F12: Agriculture & Food | G12: Coffee | H12: Bank Guarantee - Performance | I12: USD | J12: 10.22 | K12: 6.81 | L12: 6.8 | M12: 357 | N12: 45406 | O12: 45763 | P12: 4 | Q12: A | R12: 0 | S12: Stage 1 | T12: 0.0166 | U12: 0.11 | V12: 6.07 | W12: 0.89 | X12: 0.5 | Y12: Credit Agricole | Z12: No | AA12: =MIN(5,(IF(R12>90,3,IF(R12>30,2,IF(R12>0,1,0))))+IF(P12*1>=8,1,0)+IF(W12<0.7,1,0)+IF(S12="Stage 3",2,IF(S12="Stage 2",1,0))+IF(K12/J12>0.95,1,0)) -> 0 | AB12: =IF(AA12=0,"None",_xlfn.TEXTJOIN(", ",TRUE,IF(R12>90,"DPD>90",IF(R12>30,"DPD>30",IF(R12>0,"DPD>0",""))),IF(P12*1>=8,"Sub-IG Rating",""),IF(W12<0.7,"Low Collateral",""),IF(S12="Stage 3","NPL",IF(S12="Stage 2","Stage 2","")),IF(K12/J12>0.95,"High Utilization",""))) -> None
A13: TF-1012 | B13: Samman Capital | C13: National Marine Dredging | D13: UAE | E13: UAE | F13: Agriculture & Food | G13: Sugar | H13: Bank Guarantee - Performance | I13: USD | J13: 20.59 | K13: 17.58 | L13: 16 | M13: 129 | N13: 45581 | O13: 45710 | P13: 5 | Q13: BBB+ | R13: 0 | S13: Stage 1 | T13: 0.0073 | U13: 0.13 | V13: 14.76 | W13: 0.84 | X13: 0.5 | Y13: JP Morgan | Z13: No | AA13: =MIN(5,(IF(R13>90,3,IF(R13>30,2,IF(R13>0,1,0))))+IF(P13*1>=8,1,0)+IF(W13<0.7,1,0)+IF(S13="Stage 3",2,IF(S13="Stage 2",1,0))+IF(K13/J13>0.95,1,0)) -> 0 | AB13: =IF(AA13=0,"None",_xlfn.TEXTJOIN(", ",TRUE,IF(R13>90,"DPD>90",IF(R13>30,"DPD>30",IF(R13>0,"DPD>0",""))),IF(P13*1>=8,"Sub-IG Rating",""),IF(W13<0.7,"Low Collateral",""),IF(S13="Stage 3","NPL",IF(S13="Stage 2","Stage 2","")),IF(K13/J13>0.95,"High Utilization",""))) -> None
... A81: TF-1080 | B81: Beltone | C81: Sibanye Stillwater | D81: Africa | E81: South Africa | F81: Metals & Mining | G81: Gold | H81: Import LC | I81: USD | J81: 44.22 | K81: 38.35 | L81: 37.28 | M81: 174 | N81: 45340 | O81: 45514 | P81: 8 | Q81: BB | R81: 0 | S81: Stage 2 | T81: 0.108 | U81: 4.14 | V81: 25.69 | W81: 0.67 | X81: 1 | Y81: FirstRand | Z81: Yes | AA81: =MIN(5,(IF(R81>90,3,IF(R81>30,2,IF(R81>0,1,0))))+IF(P81*1>=8,1,0)+IF(W81<0.7,1,0)+IF(S81="Stage 3",2,IF(S81="Stage 2",1,0))+IF(K81/J81>0.95,1,0)) -> 3 | AB81: =IF(AA81=0,"None",_xlfn.TEXTJOIN(", ",TRUE,IF(R81>90,"DPD>90",IF(R81>30,"DPD>30",IF(R81>0,"DPD>0",""))),IF(P81*1>=8,"Sub-IG Rating",""),IF(W81<0.7,"Low Collateral",""),IF(S81="Stage 3","NPL",IF(S81="Stage 2","Stage 2","")),IF(K81/J81>0.95,"High Utilization",""))) -> Sub-IG Rating, Low Collateral, Stage 2
